[
  {
    "internal_code": "F-380-1",
    "product_code": "3402420000",
    "customs_name": "吸湿排汗整理剂",
    "components": "柔软吸湿排汗整理剂9016-88-0：90％+水：10％",
    "product_appearance": "黄色透明液体"
  },
  {
    "internal_code": "CF992C",
    "product_code": "3402420000",
    "customs_name": "吸湿排汗整理剂",
    "components": "柔软吸湿排汗整理剂9016-88-0：80％+水：20％",
    "product_appearance": "黄色液体（久置外观会变浅）"
  },
  {
    "internal_code": "CF463",
    "product_code": "3403910000",
    "customs_name": "纺织柔软剂",
    "components": "亲水软油68153-35-5：95％+水：5％",
    "product_appearance": "深黄色透明至不透明粘液（25℃）（低温不透）"
  },
  {
    "internal_code": "CF761",
    "product_code": "3402410000",
    "customs_name": "阳离子柔软剂",
    "components": "软片67701-03-5：95％+水：5％",
    "product_appearance": "米白色片状物"
  },
  {
    "internal_code": "CF934C",
    "product_code": "3402900000",
    "customs_name": "吸湿排汗整理剂",
    "components": "柔软吸湿排汗整理剂9016-88-0：90％+水：10％",
    "product_appearance": "黄色粘液（久置外观会变浅）"
  },
  {
    "internal_code": "CF1107",
    "product_code": "3403910000",
    "customs_name": "纺织柔软剂",
    "components": "亲水软油68153-35-5：95％+水：5％",
    "product_appearance": "黄色不透明液体"
  },
  {
    "internal_code": "CF357B",
    "product_code": "3403910000",
    "customs_name": "纺织柔软剂",
    "components": "亲水软油 68153-35-5：80％+水：20％",
    "product_appearance": "黄色糊状粘液"
  },
  {
    "internal_code": "CF646",
    "product_code": "3402410000",
    "customs_name": "阳离子柔软剂",
    "components": "阳离子柔软剂：80％+脂肪醇聚氧乙烯醚：20％",
    "product_appearance": "浅黄色片状物"
  },
  {
    "internal_code": "K68",
    "product_code": "3402900000",
    "customs_name": "吸湿排汗整理剂",
    "components": "柔软吸湿排汗整理剂：90％+水：10％",
    "product_appearance": "米白色不透明粘液（久置会变粘）"
  },
  {
    "internal_code": "K68-R",
    "product_code": "3402900000",
    "customs_name": "吸湿排汗整理剂",
    "components": "柔软吸湿排汗整理剂：20％+水：80％",
    "product_appearance": "米白色不透明粘液（久置会变粘）"
  },
  {
    "internal_code": "F-130D",
    "product_code": "",
    "customs_name": "阳离子柔软剂",
    "components": "软片：95％+水：5％",
    "product_appearance": "白色粘稠液"
  },
  {
    "internal_code": "F-92D",
    "product_code": "3403910000",
    "customs_name": "纺织柔软剂",
    "components": "亲水软油：95％+水：5％",
    "product_appearance": "淡黄色不透明液体"
  },
  {
    "internal_code": "CF995",
    "product_code": "3402410000",
    "customs_name": "阳离子柔软剂",
    "components": "阳离子柔软剂：80％+脂肪醇聚氧乙烯醚：20％",
    "product_appearance": "白色片状固体"
  },
  {
    "internal_code": "CF1113",
    "product_code": "3403910000",
    "customs_name": "纺织柔软剂",
    "components": "亲水软油：95％+水：5％",
    "product_appearance": "黄色糊状粘液"
  },
  {
    "internal_code": "CF140C",
    "product_code": "2905450000",
    "customs_name": "丙三醇",
    "components": "甘油：95％+水：5％",
    "product_appearance": "无色透明粘液"
  },
  {
    "internal_code": "CF261",
    "product_code": "3402900000",
    "customs_name": "非离子有机表面活性剂",
    "components": "表面活性剂9043-30-5：95％+水：5％",
    "product_appearance": "无色透明粘液（低温变朦）"
  },
  {
    "internal_code": "GY-628",
    "product_code": "3402900000",
    "customs_name": "吸湿排汗整理剂",
    "components": "表面活性剂9043-30-5：95％+水：5％",
    "product_appearance": "无色透明液体"
  },
  {
    "internal_code": "F-802B",
    "product_code": "3403910000",
    "customs_name": "非离子有机表面活性剂",
    "components": "非离子表面活性剂：95%+水：5%",
    "product_appearance": "乳白色粘稠液体（久置会分层，使用前搅拌均匀）"
  },
  {
    "internal_code": "HM158",
    "product_code": "3403910000",
    "customs_name": "纺织柔软剂",
    "components": "聚二甲基硅氧烷（硅油）50%  9016-00-6，非离子乳化剂 10% 68213-23-0，水 40% 7732-18-5",
    "product_appearance": "无色至微黄色透明液体"
  },
  {
    "internal_code": "CF141K",
    "product_code": "3402900000",
    "customs_name": "吸湿排汗整理剂",
    "components": "柔软吸湿排汗整理剂：90％+水：10％",
    "product_appearance": "米白色至浅黄色块状物"
  },
  {
    "internal_code": "K68-PAC",
    "product_code": "3402900000",
    "customs_name": "吸湿排汗整理剂",
    "components": "柔软吸湿排汗整理剂：90％+水：10％",
    "product_appearance": "白色不透明粘液（久置会变粘）"
  },
  {
    "internal_code": "K204-B",
    "product_code": "3403910000",
    "customs_name": "非离子有机表面活性剂",
    "components": "非离子表面活性剂：95%+水：5%",
    "product_appearance": "白色粘稠液体"
  },
  {
    "internal_code": "CF141H",
    "product_code": "3402900000",
    "customs_name": "吸湿排汗整理剂",
    "components": "柔软吸湿排汗整理剂：90％+水：10％",
    "product_appearance": "浅黄色颗粒状固体"
  },
  {
    "internal_code": "CF270C（软片可用）",
    "product_code": "3402410000",
    "customs_name": "阳离子柔软剂",
    "components": "阳离子柔软剂68153-35-5 ：80％+脂肪醇聚氧乙烯醚：20％",
    "product_appearance": "白色片状固体"
  },
  {
    "internal_code": "F-92Q",
    "product_code": "3403910000",
    "customs_name": "软油精",
    "components": "亲水软油：95％+水：5％",
    "product_appearance": "乳黄色不透明糊状（流动性小）"
  },
  {
    "internal_code": "CF940",
    "product_code": "3402410000",
    "customs_name": "阳离子柔软剂",
    "components": "阳离子柔软剂68153-35-5 ：80％+脂肪醇聚氧乙烯醚：20％",
    "product_appearance": "黄色片状固体"
  },
  {
    "internal_code": "LB-132D",
    "product_code": "3403910000",
    "customs_name": "纺织柔软剂",
    "components": "聚二甲基硅氧烷（硅油）50%  9016-00-6，非离子乳化剂 10% 68213-23-0，水 40% 7732-18-5",
    "product_appearance": "黄色液体"
  },
  {
    "internal_code": "LB-99B / LB-001",
    "product_code": "3403910000",
    "customs_name": "纺织柔软剂",
    "components": "聚二甲基硅氧烷（硅油）50%  9016-00-6，非离子乳化剂 10% 68213-23-0，水 40% 7732-18-5",
    "product_appearance": "黄色透明液体"
  },
  {
    "internal_code": "K223-B/P-3011-1",
    "product_code": "3403910000",
    "customs_name": "纺织柔软剂",
    "components": "聚二甲基硅氧烷（硅油）50%  9016-00-6，非离子乳化剂 10% 68213-23-0，水 40% 7732-18-5",
    "product_appearance": "浅黄色透明粘液"
  },
  {
    "internal_code": "LB-152A",
    "product_code": "3403910000",
    "customs_name": "纺织柔软剂",
    "components": "聚二甲基硅氧烷（硅油）50%  9016-00-6，非离子乳化剂 10% 68213-23-0，水 40% 7732-18-5",
    "product_appearance": "无色至浅黄色透明液体"
  },
  {
    "internal_code": "P-337",
    "product_code": "3403910000",
    "customs_name": "纺织柔软剂",
    "components": "聚二甲基硅氧烷（硅油）50%  9016-00-6，非离子乳化剂 10% 68213-23-0，水 40% 7732-18-5",
    "product_appearance": "浅黄色透明粘液"
  },
  {
    "internal_code": "LB-145D",
    "product_code": "3403910000",
    "customs_name": "纺织柔软剂",
    "components": "聚二甲基硅氧烷（硅油）50%  9016-00-6，非离子乳化剂 10% 68213-23-0，水 40% 7732-18-5",
    "product_appearance": "黄色透明液体"
  },
  {
    "internal_code": "F-182G",
    "product_code": "3403910000",
    "customs_name": "纺织柔软剂",
    "components": "聚二甲基硅氧烷（硅油）50%  9016-00-6，非离子乳化剂 10% 68213-23-0，水 40% 7732-18-5",
    "product_appearance": "无色至浅黄色透明液体（久置会变黄）"
  },
  {
    "internal_code": "F-132D",
    "product_code": "3403910000",
    "customs_name": "纺织柔软剂",
    "components": "聚二甲基硅氧烷（硅油）50%  9016-00-6，非离子乳化剂 10% 68213-23-0，水 40% 7732-18-5",
    "product_appearance": "微黄色透明液体"
  },
  {
    "internal_code": "F-88H",
    "product_code": "3403910000",
    "customs_name": "纺织柔软剂",
    "components": "聚二甲基硅氧烷（硅油）50%  9016-00-6，非离子乳化剂 10% 68213-23-0，水 40% 7732-18-5",
    "product_appearance": "浅黄色透明粘液"
  },
  {
    "internal_code": "F-152H",
    "product_code": "3403910000",
    "customs_name": "纺织柔软剂",
    "components": "聚二甲基硅氧烷（硅油）50%  9016-00-6，非离子乳化剂 10% 68213-23-0，水 40% 7732-18-5",
    "product_appearance": "无色至浅黄色透明液体"
  },
  {
    "internal_code": "F-128R",
    "product_code": "3403910000",
    "customs_name": "纺织柔软剂",
    "components": "聚二甲基硅氧烷（硅油）50%  9016-00-6，非离子乳化剂 10% 68213-23-0，水 40% 7732-18-5",
    "product_appearance": "无色至浅黄色透明液体（久置会变黄）"
  },
  {
    "internal_code": "F-182HQ",
    "product_code": "3403910000",
    "customs_name": "纺织柔软剂",
    "components": "聚二甲基硅氧烷（硅油）50%  9016-00-6，非离子乳化剂 10% 68213-23-0，水 40% 7732-18-5",
    "product_appearance": "微黄色透明至朦胧粘液"
  },
  {
    "internal_code": "F-156C",
    "product_code": "3403910000",
    "customs_name": "纺织柔软剂",
    "components": "聚二甲基硅氧烷（硅油）50%  9016-00-6，非离子乳化剂 10% 68213-23-0，水 40% 7732-18-5",
    "product_appearance": "浅色液体"
  },
  {
    "internal_code": "LB-132D-1",
    "product_code": "3403910000",
    "customs_name": "纺织柔软剂",
    "components": "聚二甲基硅氧烷（硅油）50%  9016-00-6，非离子乳化剂 10% 68213-23-0，水 40% 7732-18-5",
    "product_appearance": "浅黄色透明液体（久置会变黄）"
  },
  {
    "internal_code": "T68-A",
    "product_code": "3403910000",
    "customs_name": "纺织柔软剂",
    "components": "聚二甲基硅氧烷（硅油）50%  9016-00-6，非离子乳化剂 10% 68213-23-0，水 40% 7732-18-5",
    "product_appearance": "无色至黄色透明粘液"
  },
  {
    "internal_code": "F-369-2",
    "product_code": "3403910000",
    "customs_name": "纺织柔软剂",
    "components": "聚二甲基硅氧烷（硅油）50%  9016-00-6，非离子乳化剂 10% 68213-23-0，水 40% 7732-18-5",
    "product_appearance": "无色至浅黄色透明液体"
  },
  {
    "internal_code": "F-152",
    "product_code": "3403910000",
    "customs_name": "纺织柔软剂",
    "components": "聚二甲基硅氧烷（硅油）50%  9016-00-6，非离子乳化剂 10% 68213-23-0，水 40% 7732-18-5",
    "product_appearance": "无色透明液体"
  },
  {
    "internal_code": "F-369",
    "product_code": "3403910000",
    "customs_name": "纺织柔软剂",
    "components": "聚二甲基硅氧烷（硅油）50%  9016-00-6，非离子乳化剂 10% 68213-23-0，水 40% 7732-18-5",
    "product_appearance": "黄色透明液体"
  },
  {
    "internal_code": "LB-369",
    "product_code": "3403910000",
    "customs_name": "纺织柔软剂",
    "components": "聚二甲基硅氧烷（硅油）50%  9016-00-6，非离子乳化剂 10% 68213-23-0，水 40% 7732-18-5",
    "product_appearance": "黄色透明粘液"
  },
  {
    "internal_code": "P-4019-5",
    "product_code": "3403910000",
    "customs_name": "纺织柔软剂",
    "components": "聚二甲基硅氧烷（硅油）50%  9016-00-6，非离子乳化剂 10% 68213-23-0，水 40% 7732-18-5",
    "product_appearance": "浅黄色粘液"
  },
  {
    "internal_code": "F-128Q",
    "product_code": "3403910000",
    "customs_name": "纺织柔软剂",
    "components": "聚二甲基硅氧烷（硅油）50%  9016-00-6，非离子乳化剂 10% 68213-23-0，水 40% 7732-18-5",
    "product_appearance": "无色至浅黄色透明液体"
  },
  {
    "internal_code": "K220-T",
    "product_code": "3403910000",
    "customs_name": "纺织柔软剂",
    "components": "聚二甲基硅氧烷（硅油）50%  9016-00-6，非离子乳化剂 10% 68213-23-0，水 40% 7732-18-5",
    "product_appearance": "无色至浅黄色透明液体"
  },
  {
    "internal_code": "P-213B",
    "product_code": "3403910000",
    "customs_name": "纺织柔软剂",
    "components": "聚二甲基硅氧烷（硅油）50%  9016-00-6，非离子乳化剂 10% 68213-23-0，水 40% 7732-18-5",
    "product_appearance": "无色至浅黄色液体"
  },
  {
    "internal_code": "F-399H",
    "product_code": "3403910000",
    "customs_name": "纺织柔软剂",
    "components": "聚二甲基硅氧烷（硅油）50%  9016-00-6，非离子乳化剂 10% 68213-23-0，水 40% 7732-18-5",
    "product_appearance": "无色至浅黄色透明液体（久置会变黄）"
  },
  {
    "internal_code": "P-303A",
    "product_code": "3403910000",
    "customs_name": "纺织柔软剂",
    "components": "聚二甲基硅氧烷（硅油）50%  9016-00-6，非离子乳化剂 10% 68213-23-0，水 40% 7732-18-5",
    "product_appearance": "无色至浅黄色透明液体"
  },
  {
    "internal_code": "F-397-2",
    "product_code": "3403910000",
    "customs_name": "纺织柔软剂",
    "components": "聚二甲基硅氧烷（硅油）50%  9016-00-6，非离子乳化剂 10% 68213-23-0，水 40% 7732-18-5",
    "product_appearance": "浅黄色粘液（低温变朦，久置变黄）"
  },
  {
    "internal_code": "T41-MD",
    "product_code": "3403910000",
    "customs_name": "纺织柔软剂",
    "components": "聚二甲基硅氧烷（硅油）50%  9016-00-6，非离子乳化剂 10% 68213-23-0，水 40% 7732-18-5",
    "product_appearance": "无色透明粘液（久置或高温会变朦、变粘）"
  },
  {
    "internal_code": "F-145D-1",
    "product_code": "3403910000",
    "customs_name": "纺织柔软剂",
    "components": "聚二甲基硅氧烷（硅油）50%  9016-00-6，非离子乳化剂 10% 68213-23-0，水 40% 7732-18-5",
    "product_appearance": "浅黄色透明液体"
  },
  {
    "internal_code": "F-369-6",
    "product_code": "3403910000",
    "customs_name": "纺织柔软剂",
    "components": "聚二甲基硅氧烷（硅油）50%  9016-00-6，非离子乳化剂 10% 68213-23-0，水 40% 7732-18-5",
    "product_appearance": "无色至浅黄色透明液体"
  },
  {
    "internal_code": "HM142",
    "product_code": "3403910000",
    "customs_name": "纺织柔软剂",
    "components": "聚二甲基硅氧烷（硅油）50%  9016-00-6，非离子乳化剂 10% 68213-23-0，水 40% 7732-18-5",
    "product_appearance": "无色透明粘液"
  },
  {
    "internal_code": "F-152-1",
    "product_code": "3403910000",
    "customs_name": "纺织柔软剂",
    "components": "聚二甲基硅氧烷（硅油）50%  9016-00-6，非离子乳化剂 10% 68213-23-0，水 40% 7732-18-5",
    "product_appearance": "黄色透明粘液"
  },
  {
    "internal_code": "P-2010-1",
    "product_code": "3403910000",
    "customs_name": "纺织柔软剂",
    "components": "聚二甲基硅氧烷（硅油）50%  9016-00-6，非离子乳化剂 10% 68213-23-0，水 40% 7732-18-5",
    "product_appearance": "无色至黄色透明粘液(久置会变黄)"
  },
  {
    "internal_code": "F-38A",
    "product_code": "3403910000",
    "customs_name": "纺织柔软剂",
    "components": "聚二甲基硅氧烷（硅油）50%  9016-00-6，非离子乳化剂 10% 68213-23-0，水 40% 7732-18-5",
    "product_appearance": "无色至浅黄色透明液体（久置会变黄）"
  },
  {
    "internal_code": "F-145D",
    "product_code": "3403910000",
    "customs_name": "纺织柔软剂",
    "components": "聚二甲基硅氧烷（硅油）50%  9016-00-6，非离子乳化剂 10% 68213-23-0，水 40% 7732-18-5",
    "product_appearance": "无色至浅黄色透明液体"
  },
  {
    "internal_code": "F-398-2",
    "product_code": "3403910000",
    "customs_name": "纺织柔软剂",
    "components": "聚二甲基硅氧烷（硅油）50%  9016-00-6，非离子乳化剂 10% 68213-23-0，水 40% 7732-18-5",
    "product_appearance": "浅黄色透明液体"
  },
  {
    "internal_code": "LB-303H",
    "product_code": "3403910000",
    "customs_name": "纺织柔软剂",
    "components": "聚二甲基硅氧烷（硅油）50%  9016-00-6，非离子乳化剂 10% 68213-23-0，水 40% 7732-18-5",
    "product_appearance": "无色透明液体"
  },
  {
    "internal_code": "K12-L",
    "product_code": "3403910000",
    "customs_name": "纺织柔软剂",
    "components": "聚二甲基硅氧烷（硅油）50%  9016-00-6，非离子乳化剂 10% 68213-23-0，水 40% 7732-18-5",
    "product_appearance": "浅黄色粘液"
  },
  {
    "internal_code": "F-333-1A",
    "product_code": "3403910000",
    "customs_name": "纺织柔软剂",
    "components": "聚二甲基硅氧烷（硅油）50%  9016-00-6，非离子乳化剂 10% 68213-23-0，水 40% 7732-18-5",
    "product_appearance": "黄色液体"
  },
  {
    "internal_code": "P-236DA",
    "product_code": "3403910000",
    "customs_name": "纺织柔软剂",
    "components": "聚二甲基硅氧烷（硅油）50%  9016-00-6，非离子乳化剂 10% 68213-23-0，水 40% 7732-18-5",
    "product_appearance": "无色透明液体"
  },
  {
    "internal_code": "F-369-3",
    "product_code": "3403910000",
    "customs_name": "纺织柔软剂",
    "components": "聚二甲基硅氧烷（硅油）50%  9016-00-6，非离子乳化剂 10% 68213-23-0，水 40% 7732-18-5",
    "product_appearance": "浅黄色透明液体"
  },
  {
    "internal_code": "T104",
    "product_code": "3403910000",
    "customs_name": "纺织柔软剂",
    "components": "聚二甲基硅氧烷（硅油）50%  9016-00-6，非离子乳化剂 10% 68213-23-0，水 40% 7732-18-5",
    "product_appearance": "无色透明粘液（久置或高温会变粘）"
  },
  {
    "internal_code": "F-152A",
    "product_code": "3403910000",
    "customs_name": "纺织柔软剂",
    "components": "聚二甲基硅氧烷（硅油）50%  9016-00-6，非离子乳化剂 10% 68213-23-0，水 40% 7732-18-5",
    "product_appearance": "无色透明液体"
  },
  {
    "internal_code": "F-369H",
    "product_code": "3403910000",
    "customs_name": "纺织柔软剂",
    "components": "聚二甲基硅氧烷（硅油）50%  9016-00-6，非离子乳化剂 10% 68213-23-0，水 40% 7732-18-5",
    "product_appearance": "黄色透明粘液"
  },
  {
    "internal_code": "F-132H",
    "product_code": "3403910000",
    "customs_name": "纺织柔软剂",
    "components": "聚二甲基硅氧烷（硅油）50%  9016-00-6，非离子乳化剂 10% 68213-23-0，水 40% 7732-18-5",
    "product_appearance": "无色至浅黄色透明粘液（久置变黄）"
  },
  {
    "internal_code": "LB-317B",
    "product_code": "3403910000",
    "customs_name": "纺织柔软剂",
    "components": "聚二甲基硅氧烷（硅油）50%  9016-00-6，非离子乳化剂 10% 68213-23-0，水 40% 7732-18-5",
    "product_appearance": "无色至浅黄色透明液体"
  },
  {
    "internal_code": "LB-369-1",
    "product_code": "3403910000",
    "customs_name": "纺织柔软剂",
    "components": "聚二甲基硅氧烷（硅油）50%  9016-00-6，非离子乳化剂 10% 68213-23-0，水 40% 7732-18-5",
    "product_appearance": "无色至浅黄色透明粘液（久置变黄）"
  },
  {
    "internal_code": "P-2005",
    "product_code": "3403910000",
    "customs_name": "纺织柔软剂",
    "components": "聚二甲基硅氧烷（硅油）50%  9016-00-6，非离子乳化剂 10% 68213-23-0，水 40% 7732-18-5",
    "product_appearance": "黄色透明粘液"
  },
  {
    "internal_code": "P-2010",
    "product_code": "3403910000",
    "customs_name": "纺织柔软剂",
    "components": "聚二甲基硅氧烷（硅油）50%  9016-00-6，非离子乳化剂 10% 68213-23-0，水 40% 7732-18-5",
    "product_appearance": "黄色透明粘液"
  },
  {
    "internal_code": "P-404CD",
    "product_code": "3403910000",
    "customs_name": "纺织柔软剂",
    "components": "聚二甲基硅氧烷（硅油）50%  9016-00-6，非离子乳化剂 10% 68213-23-0，水 40% 7732-18-5",
    "product_appearance": "浅黄色粘液"
  },
  {
    "internal_code": "T30-A",
    "product_code": "3403910000",
    "customs_name": "纺织柔软剂",
    "components": "聚二甲基硅氧烷（硅油）50%  9016-00-6，非离子乳化剂 10% 68213-23-0，水 40% 7732-18-5",
    "product_appearance": "无色至浅黄色透明粘液"
  },
  {
    "internal_code": "P-2006",
    "product_code": "3403910000",
    "customs_name": "纺织柔软剂",
    "components": "聚二甲基硅氧烷（硅油）50%  9016-00-6，非离子乳化剂 10% 68213-23-0，水 40% 7732-18-5",
    "product_appearance": "黄色透明粘液"
  },
  {
    "internal_code": "P-331",
    "product_code": "3403910000",
    "customs_name": "纺织柔软剂",
    "components": "聚二甲基硅氧烷（硅油）50%  9016-00-6，非离子乳化剂 10% 68213-23-0，水 40% 7732-18-5",
    "product_appearance": "浅黄色透明粘液（久置变黄）"
  },
  {
    "internal_code": "F-397H",
    "product_code": "3403910000",
    "customs_name": "纺织柔软剂",
    "components": "聚二甲基硅氧烷（硅油）50%  9016-00-6，非离子乳化剂 10% 68213-23-0，水 40% 7732-18-5",
    "product_appearance": "浅黄色透明液体（久置会变黄）"
  },
  {
    "internal_code": "K220-T-6",
    "product_code": "3403910000",
    "customs_name": "纺织柔软剂",
    "components": "聚二甲基硅氧烷（硅油）50%  9016-00-6，非离子乳化剂 10% 68213-23-0，水 40% 7732-18-5",
    "product_appearance": "无色至浅黄色透明液体"
  },
  {
    "internal_code": "F-186",
    "product_code": "3403910000",
    "customs_name": "纺织柔软剂",
    "components": "聚二甲基硅氧烷（硅油）50%  9016-00-6，非离子乳化剂 10% 68213-23-0，水 40% 7732-18-5",
    "product_appearance": "白色粘稠液"
  },
  {
    "internal_code": "GY-629",
    "product_code": "3403910000",
    "customs_name": "纺织柔软剂",
    "components": "聚二甲基硅氧烷（硅油）50%  9016-00-6，非离子乳化剂 10% 68213-23-0，水 40% 7732-18-5",
    "product_appearance": "半透明粘液"
  },
  {
    "internal_code": "F-89D",
    "product_code": "3403910000",
    "customs_name": "纺织柔软剂",
    "components": "聚二甲基硅氧烷（硅油）50%  9016-00-6，非离子乳化剂 10% 68213-23-0，水 40% 7732-18-5",
    "product_appearance": "无色至浅黄色透明液体（久置变黄）"
  },
  {
    "internal_code": "P-404A",
    "product_code": "3403910000",
    "customs_name": "纺织柔软剂",
    "components": "聚二甲基硅氧烷（硅油）50%  9016-00-6，非离子乳化剂 10% 68213-23-0，水 40% 7732-18-5",
    "product_appearance": "浅色粘液"
  },
  {
    "internal_code": "P-4019",
    "product_code": "3403910000",
    "customs_name": "纺织柔软剂",
    "components": "聚二甲基硅氧烷（硅油）50%  9016-00-6，非离子乳化剂 10% 68213-23-0，水 40% 7732-18-5",
    "product_appearance": "浅黄色粘液"
  },
  {
    "internal_code": "F-343",
    "product_code": "3403910000",
    "customs_name": "纺织柔软剂",
    "components": "聚二甲基硅氧烷（硅油）50%  9016-00-6，非离子乳化剂 10% 68213-23-0，水 40% 7732-18-5",
    "product_appearance": "无色至浅黄色透明液体"
  },
  {
    "internal_code": "F-373",
    "product_code": "3403910000",
    "customs_name": "纺织柔软剂",
    "components": "聚二甲基硅氧烷（硅油）50%  9016-00-6，非离子乳化剂 10% 68213-23-0，水 40% 7732-18-5",
    "product_appearance": "白色液体"
  },
  {
    "internal_code": "CF255D",
    "product_code": "3403910000",
    "customs_name": "纺织柔软剂",
    "components": "聚二甲基硅氧烷（硅油）50%  9016-00-6，非离子乳化剂 10% 68213-23-0，水 40% 7732-18-5",
    "product_appearance": "无色透明粘液"
  },
  {
    "internal_code": "GY-532",
    "product_code": "3403910000",
    "customs_name": "纺织柔软剂",
    "components": "聚二甲基硅氧烷（硅油）50%  9016-00-6，非离子乳化剂 10% 68213-23-0，水 40% 7732-18-5",
    "product_appearance": "无色透明液体"
  },
  {
    "internal_code": "F-155H",
    "product_code": "3403910000",
    "customs_name": "纺织柔软剂",
    "components": "聚二甲基硅氧烷（硅油）50%  9016-00-6，非离子乳化剂 10% 68213-23-0，水 40% 7732-18-5",
    "product_appearance": "黄色透明粘液（久置变黄）"
  },
  {
    "internal_code": "LP-306-1",
    "product_code": "3403910000",
    "customs_name": "纺织柔软剂",
    "components": "聚二甲基硅氧烷（硅油）50%  9016-00-6，非离子乳化剂 10% 68213-23-0，水 40% 7732-18-5",
    "product_appearance": "黄色透明粘液（久置变黄）"
  },
  {
    "internal_code": "F-399A-1",
    "product_code": "3403910000",
    "customs_name": "纺织柔软剂",
    "components": "聚二甲基硅氧烷（硅油）50%  9016-00-6，非离子乳化剂 10% 68213-23-0，水 40% 7732-18-5",
    "product_appearance": "无色透明液体"
  },
  {
    "internal_code": "K311",
    "product_code": "3403910000",
    "customs_name": "纺织柔软剂",
    "components": "聚二甲基硅氧烷（硅油）50%  9016-00-6，非离子乳化剂 10% 68213-23-0，水 40% 7732-18-5",
    "product_appearance": "白色液体（久置会分层）"
  },
  {
    "internal_code": "F-369-5",
    "product_code": "3403910000",
    "customs_name": "纺织柔软剂",
    "components": "聚二甲基硅氧烷（硅油）50%  9016-00-6，非离子乳化剂 10% 68213-23-0，水 40% 7732-18-5",
    "product_appearance": "无色透明液体 （久置变黄）"
  },
  {
    "internal_code": "B-40EA",
    "product_code": "3402900000",
    "customs_name": "固色剂",
    "components": "双酚S：80-09-1；52%\n分散剂：26545-58-4；3%\n水：7732-18-5；45%",
    "product_appearance": "棕黑色透明粘液"
  },
  {
    "internal_code": "GS17-02DA",
    "product_code": "3402900000",
    "customs_name": "固色剂",
    "components": "双酚S：80-09-1；52%\n分散剂：26545-58-4；3%\n水：7732-18-5；45%",
    "product_appearance": "棕黑色透明液"
  },
  {
    "internal_code": "B-66A",
    "product_code": "3402410000",
    "customs_name": "固色剂",
    "components": "双酚S：80-09-1；55%\n水：7732-18-5；45%",
    "product_appearance": "棕黑色透明粘液"
  },
  {
    "internal_code": "GS25-01",
    "product_code": "3402900000",
    "customs_name": "固色剂",
    "components": "双酚S：80-09-1；55%\n水：7732-18-5；45%",
    "product_appearance": "棕黑色透明粘液"
  },
  {
    "internal_code": "K26",
    "product_code": "3402900000",
    "customs_name": "固色剂",
    "components": "双酚S：80-09-1；55%\n水：7732-18-5；45%",
    "product_appearance": "棕黑色透明粘液"
  },
  {
    "internal_code": "GW55-02",
    "product_code": "3402410000",
    "customs_name": "固色剂",
    "components": "水：7732-18-5，55%\n二甲基二烯丙基氯化铵：26062-79-3，45%",
    "product_appearance": "暗黄色透明粘液"
  },
  {
    "internal_code": "GW95-01",
    "product_code": "3402410000",
    "customs_name": "固色剂",
    "components": "水：7732-18-5，55%\n二甲基二烯丙基氯化铵：26062-79-3，45%",
    "product_appearance": "无色或微黄色透明粘液"
  },
  {
    "internal_code": "K1-WPB/ / GW52-01",
    "product_code": "3402410000",
    "customs_name": "固色剂",
    "components": "水：7732-18-5，55%\n二甲基二烯丙基氯化铵：26062-79-3，45%",
    "product_appearance": "黄色透明粘液"
  },
  {
    "internal_code": "T16-HP",
    "product_code": "2921290090",
    "customs_name": "固色剂",
    "components": "二甘醇：111-46-6，23%\n甘油：56-81-5，40%\n水：7732-18-5，37%",
    "product_appearance": "黄色透明粘液"
  },
  {
    "internal_code": "B-70H",
    "product_code": "3402410000",
    "customs_name": "固色剂",
    "components": "水：7732-18-5，60%\n二甲基二烯丙基氯化铵：26062-79-3，40%",
    "product_appearance": "浅黄色透明粘液"
  },
  {
    "internal_code": "T16",
    "product_code": "2921290090",
    "customs_name": "固色剂",
    "components": "二甘醇：111-46-6，23%\n甘油：56-81-5，28%\n水：7732-18-5，49%",
    "product_appearance": "黄色透明粘液"
  },
  {
    "internal_code": "GS55-01A",
    "product_code": "2942000000",
    "customs_name": "其他有机化合物",
    "components": "单宁酸：1401-55-4；30%\n分散剂：26545-58-4；3%\n水：7732-18-5；67%",
    "product_appearance": "棕黑色透明液"
  },
  {
    "internal_code": "B-70AP",
    "product_code": "3402410000",
    "customs_name": "固色剂",
    "components": "水：7732-18-5，55%\n二甲基二烯丙基氯化铵：26062-79-3，45%",
    "product_appearance": "黄色透明粘液"
  },
  {
    "internal_code": "GS54-01",
    "product_code": "2942000000",
    "customs_name": "固色剂",
    "components": "十二烷基苯磺酸钠：25155-30-0，30%\n分散剂：26545-58-4，3%\n水：7732-18-5，67%",
    "product_appearance": "棕黑色透明液"
  },
  {
    "internal_code": "B-71",
    "product_code": "3402410000",
    "customs_name": "固色剂",
    "components": "二甲基二烯丙基氯化铵：26062-79-3，40%\n水：7732-18-5，60%",
    "product_appearance": "无色至淡黄色透明粘液"
  },
  {
    "internal_code": "K230",
    "product_code": "3402900000",
    "customs_name": "固色剂",
    "components": "水：7732-18-5；65%\n双酚S：80-09-1，35%",
    "product_appearance": "棕色透明液"
  },
  {
    "internal_code": "GC18-02A",
    "product_code": "2921290090",
    "customs_name": "固色剂",
    "components": "二甘醇：111-46-6，22%\n甘油：56-81-5，40%\n水：7732-18-5，38%",
    "product_appearance": "黄色透明粘液"
  },
  {
    "internal_code": "B-59BK",
    "product_code": "3402410000",
    "customs_name": "固色剂",
    "components": "二甲基二烯丙基氯化铵：26062-79-3，50%\n水：7732-18-5，50%",
    "product_appearance": "黄色透明粘液"
  },
  {
    "internal_code": "K1-Z",
    "product_code": "3402410000",
    "customs_name": "固色剂",
    "components": "水：7732-18-5，55%\n二甲基二烯丙基氯化铵：26062-79-3，45%",
    "product_appearance": "棕色透明粘液"
  },
  {
    "internal_code": "K86-W",
    "product_code": "3402410000",
    "customs_name": "固色剂",
    "components": "水：7732-18-5，50%\n二甲基二烯丙基氯化铵：26062-79-3，50%",
    "product_appearance": "黄色透明粘液"
  },
  {
    "internal_code": "B-70",
    "product_code": "3402410000",
    "customs_name": "固色剂",
    "components": "水：7732-18-5，55%\n二甲基二烯丙基氯化铵：26062-79-3，45%",
    "product_appearance": "黄色透明粘液"
  },
  {
    "internal_code": "B-70W",
    "product_code": "3402410000",
    "customs_name": "固色剂",
    "components": "水：7732-18-5，45%\n二甲基二烯丙基氯化铵：26062-79-3，55%",
    "product_appearance": "黄色透明粘液"
  },
  {
    "internal_code": "K1-ZQ",
    "product_code": "3402410000",
    "customs_name": "固色剂",
    "components": "水：7732-18-5，50%\n二甲基二烯丙基氯化铵：26062-79-3，50%",
    "product_appearance": "黄色透明粘液"
  },
  {
    "internal_code": "B-59BC",
    "product_code": "3402410000",
    "customs_name": "固色剂",
    "components": "二甲基二烯丙基氯化铵：26062-79-3，50%\n水：7732-18-5，50%",
    "product_appearance": "黄色透明粘液"
  },
  {
    "internal_code": "B-90FC",
    "product_code": "3402410000",
    "customs_name": "固色剂",
    "components": "水：7732-18-5，49%\n二甲基二烯丙基氯化铵：26062-79-3，51%",
    "product_appearance": "黄色透明粘液"
  },
  {
    "internal_code": "T16-H / GC18-03",
    "product_code": "2921290090",
    "customs_name": "固色剂",
    "components": "二甘醇：111-46-6，23%\n甘油：56-81-5，45%\n水：7732-18-5，32%",
    "product_appearance": "黄色透明粘液"
  },
  {
    "internal_code": "GS54-01A",
    "product_code": "2942000000",
    "customs_name": "固色剂",
    "components": "十二烷基苯磺酸钠：25155-30-0，30%\n分散剂：26545-58-4，3%\n水：7732-18-5，67%",
    "product_appearance": "棕黑色透明液"
  },
  {
    "internal_code": "B-59Y",
    "product_code": "3402410000",
    "customs_name": "固色剂",
    "components": "二甲基二烯丙基氯化铵：26062-79-3，50%\n水：7732-18-5，50%",
    "product_appearance": "黄色透明粘液"
  },
  {
    "internal_code": "B-70HY",
    "product_code": "3402410000",
    "customs_name": "固色剂",
    "components": "水：7732-18-5，49%\n二甲基二烯丙基氯化铵：26062-79-3，51%",
    "product_appearance": "浅黄色透明粘液"
  },
  {
    "internal_code": "GC18-02",
    "product_code": "2921290090",
    "customs_name": "固色剂",
    "components": "二甘醇：111-46-6，17%\n甘油：56-81-5，30%\n水：7732-18-5，53%",
    "product_appearance": "黄色透明粘液"
  },
  {
    "internal_code": "K116-G",
    "product_code": "2923900090",
    "customs_name": "固色剂",
    "components": "二甲基二烯丙基氯化铵：26062-79-3，46%\n水：7732-18-5，54%",
    "product_appearance": "无色透明粘液"
  },
  {
    "internal_code": "T13-C",
    "product_code": "2921290090",
    "customs_name": "固色剂",
    "components": "二甲基二烯丙基氯化铵：26062-79-3，30%\n水：7732-18-5，70%",
    "product_appearance": "黄色透明粘液"
  },
  {
    "internal_code": "GZ24-02",
    "product_code": "3402900000",
    "customs_name": "固色剂",
    "components": "双酚S：80-09-1，35%\n水：7732-18-5，65%",
    "product_appearance": "棕色透明液"
  },
  {
    "internal_code": "GZ24-03",
    "product_code": "3402900000",
    "customs_name": "固色剂",
    "components": "双酚S：80-09-1，35%\n水：7732-18-5，65%",
    "product_appearance": "棕色透明液"
  },
  {
    "internal_code": "B-90W",
    "product_code": "3402410000",
    "customs_name": "固色剂",
    "components": "二甲基二烯丙基氯化铵：26062-79-3，51%\n水：7732-18-5，49%",
    "product_appearance": "黄色透明粘液"
  },
  {
    "internal_code": "GS17-04A/ B",
    "product_code": "3402900000",
    "customs_name": "固色剂",
    "components": "酚醛树脂：9003-35-4；50%\n分散剂：26545-58-4；5%\n水：7732-18-5；35%",
    "product_appearance": "棕黑色透明粘液"
  },
  {
    "internal_code": "B-90P",
    "product_code": "3402410000",
    "customs_name": "固色剂",
    "components": "二甲基二烯丙基氯化铵：26062-79-3，54%\n水：7732-18-5，46%",
    "product_appearance": "黄色带红光透明粘液"
  },
  {
    "internal_code": "K1-ZF",
    "product_code": "3402410000",
    "customs_name": "固色剂",
    "components": "水：7732-18-5，78%\n聚二甲基二烯丙基氯化铵：26062-79-3，22%",
    "product_appearance": "暗黄色透明粘液"
  },
  {
    "internal_code": "T16-HMB",
    "product_code": "2921290090",
    "customs_name": "固色剂",
    "components": "二甘醇：111-46-6，9%\n甘油：56-81-5，24%\n水：7732-18-5，65%",
    "product_appearance": "黄色透明粘液"
  },
  {
    "internal_code": "K116-GH",
    "product_code": "2923900090",
    "customs_name": "固色剂",
    "components": "二甲基二烯丙基氯化铵：26062-79-3，54%\n水：7732-18-5，46%",
    "product_appearance": "无色透明粘液"
  },
  {
    "internal_code": "B-90FCA",
    "product_code": "3402410000",
    "customs_name": "固色剂",
    "components": "水：7732-18-5，73%\n二甲基二烯丙基氯化铵：26062-79-3，27%",
    "product_appearance": "黄色透明粘液"
  },
  {
    "internal_code": "K70-HZ",
    "product_code": "2921290090",
    "customs_name": "固色剂",
    "components": "二甘醇：111-46-6，6%\n甘油：56-81-5，15%\n水：7732-18-5，79%",
    "product_appearance": "黄色透明粘液"
  },
  {
    "internal_code": "B-90F",
    "product_code": "3402410000",
    "customs_name": "固色剂",
    "components": "水：7732-18-5，47%\n二甲基二烯丙基氯化铵：26062-79-3，53%",
    "product_appearance": "黄色透明粘液"
  },
  {
    "internal_code": "T13-CA",
    "product_code": "2921290090",
    "customs_name": "固色剂",
    "components": "二甲基二烯丙基氯化铵：26062-79-3，34%\n水：7732-18-5，66%",
    "product_appearance": "黄色透明粘液"
  },
  {
    "internal_code": "B-50",
    "product_code": "3906909090",
    "customs_name": "其他初级形状的丙烯酸聚合物",
    "components": "聚丙烯酸钠：9003-04-7；40%\n水：7732-18-5；60%",
    "product_appearance": "无色至淡黄色透明粘液"
  },
  {
    "internal_code": "GW84-01",
    "product_code": "3402410000",
    "customs_name": "固色剂",
    "components": "聚二甲基二烯丙基氯化铵：26062-79-3，34%\n水：7732-18-5，66%",
    "product_appearance": "黄色透明粘液"
  },
  {
    "internal_code": "B-59BCD",
    "product_code": "3402410000",
    "customs_name": "固色剂",
    "components": "二甲基二烯丙基氯化铵：26062-79-3，50%\n水：7732-18-5，50%",
    "product_appearance": "黄色透明粘液"
  },
  {
    "internal_code": "A-104",
    "product_code": "3402420000",
    "customs_name": "非离子有机表面活性剂",
    "components": "非离子表面活性剂68603-25-8  20%\n脂肪醇聚氧烷基醚68439-46-3  20%\n水   60%",
    "product_appearance": "黄色不透明液体"
  },
  {
    "internal_code": "A-109",
    "product_code": "3402420000",
    "customs_name": "非离子有机表面活性剂",
    "components": "非离子表面活性剂68603-25-8  15%\n脂肪醇聚氧烷基醚68439-46-3  25%\n水   60%",
    "product_appearance": "米白色乳液（带灰）"
  },
  {
    "internal_code": "A-105",
    "product_code": "3402420000",
    "customs_name": "非离子有机表面活性剂",
    "components": "非离子表面活性剂68603-25-8  15%\n脂肪醇聚氧烷基醚68439-46-3  25%\n水   60%",
    "product_appearance": "米白色乳液（带灰）"
  },
  {
    "internal_code": "A-10FH",
    "product_code": "2942000000",
    "customs_name": "螯合分散剂",
    "components": "三聚磷酸钠 7758-29-4 30%\n葡萄糖酸钠527-07-1  30%\n水  40%",
    "product_appearance": "黄色透明液"
  },
  {
    "internal_code": "A-10K",
    "product_code": "2942000000",
    "customs_name": "螯合分散剂",
    "components": "三聚磷酸钠 7758-29-4 15%\n葡萄糖酸钠527-07-1  15%\n水  70%",
    "product_appearance": "无色透明液"
  },
  {
    "internal_code": "CF022B",
    "product_code": "2942000000",
    "customs_name": "螯合分散剂",
    "components": "三聚磷酸钠 7758-29-4 15%\n葡萄糖酸钠527-07-1  15%\n水  70%",
    "product_appearance": "浅黄色透明液"
  },
  {
    "internal_code": "A-16E",
    "product_code": "3402420000",
    "customs_name": "渗透剂",
    "components": "非离子表面活性剂68603-25-8 10%\n脂肪醇聚氧烷基醚68439-46-3  5%\n水 85%",
    "product_appearance": "无色透明液"
  },
  {
    "internal_code": "A-18CB",
    "product_code": "3402420000",
    "customs_name": "渗透剂",
    "components": "非离子表面活性剂68603-25-8  15%\n脂肪醇聚氧烷基醚68439-46-3  10%\n水   75%",
    "product_appearance": "无色透明液"
  },
  {
    "internal_code": "A-18G",
    "product_code": "3402420000",
    "customs_name": "渗透剂",
    "components": "非离子表面活性剂68603-25-8  40%\n脂肪醇聚氧烷基醚68439-46-3  35%\n水 25%",
    "product_appearance": "无色透明液"
  },
  {
    "internal_code": "A-21",
    "product_code": "3402420000",
    "customs_name": "渗透剂",
    "components": "非离子表面活性剂68603-25-8  15%\n脂肪醇聚氧烷基醚68439-46-3  10%\n水   75%",
    "product_appearance": "黄色至深黄色粘液  （会有沉底）"
  },
  {
    "internal_code": "A-34A",
    "product_code": "3402420000",
    "customs_name": "精练剂",
    "components": "非离子表面活性剂68603-25-8 20%\n脂肪醇聚氧烷基醚68439-46-3 20%\n水 60%",
    "product_appearance": "无色至浅色透明液"
  },
  {
    "internal_code": "A-37B",
    "product_code": "2942000000",
    "customs_name": "螯合分散剂",
    "components": "HEDP 2809-21-4  10%\n葡萄糖酸钠527-07-1   20%\n水  70%",
    "product_appearance": "黄色透明液"
  },
  {
    "internal_code": "A-37BA",
    "product_code": "2942000000",
    "customs_name": "螯合分散剂",
    "components": "HEDP 2809-21-4  5%\n葡萄糖酸钠527-07-1  23%\n水 72%",
    "product_appearance": "棕色透明液"
  },
  {
    "internal_code": "A-49",
    "product_code": "3402420000",
    "customs_name": "精练剂",
    "components": "非离子表面活性剂68603-25-8 15%\n脂肪醇聚氧烷基醚68439-46-3  15%\n水  70%",
    "product_appearance": "蓝色透明液体"
  },
  {
    "internal_code": "A-49H",
    "product_code": "3402420000",
    "customs_name": "精练剂",
    "components": "非离子表面活性剂68603-25-8 10%\n脂肪醇聚氧烷基醚68439-46-3  25%\n水 65%",
    "product_appearance": "蓝色透明液体"
  },
  {
    "internal_code": "A-50C",
    "product_code": "3402420000",
    "customs_name": "渗透剂",
    "components": "非离子表面活性剂68603-25-8 15%\n脂肪醇聚氧烷基醚68439-46-3  15%\n水  70%",
    "product_appearance": "无色透明液"
  },
  {
    "internal_code": "A-60",
    "product_code": "3402420000",
    "customs_name": "渗透剂",
    "components": "非离子表面活性剂68603-25-8 40%\n脂肪醇聚氧烷基醚68439-46-3 40%\n水 20%",
    "product_appearance": "无色透明液"
  },
  {
    "internal_code": "A-60AH",
    "product_code": "3402420000",
    "customs_name": "渗透剂",
    "components": "非离子表面活性剂68603-25-8 60%\n脂肪醇聚氧烷基醚68439-46-3 20%\n水 20%",
    "product_appearance": "无色透明液"
  },
  {
    "internal_code": "A-60ALD",
    "product_code": "3402420000",
    "customs_name": "渗透剂",
    "components": "非离子表面活性剂68603-25-8 20%\n脂肪醇聚氧烷基醚68439-46-3 30%\n水 50%",
    "product_appearance": "无色至浅色透明液"
  },
  {
    "internal_code": "A-60E",
    "product_code": "3402420000",
    "customs_name": "渗透剂",
    "components": "非离子表面活性剂68603-25-8 10%\n脂肪醇聚氧烷基醚68439-46-3  10%\n水 80%",
    "product_appearance": "无色透明液"
  },
  {
    "internal_code": "A-60H",
    "product_code": "3402420000",
    "customs_name": "渗透剂",
    "components": "非离子表面活性剂68603-25-8 20%\n脂肪醇聚氧烷基醚68439-46-3 50%\n水 30%",
    "product_appearance": "无色至浅色透明液"
  },
  {
    "internal_code": "A-60QA",
    "product_code": "3402420000",
    "customs_name": "渗透剂",
    "components": "非离子表面活性剂68603-25-8 30%\n脂肪醇聚氧烷基醚68439-46-3 10%\n水 60%",
    "product_appearance": "无色透明液"
  },
  {
    "internal_code": "A-60S",
    "product_code": "3402420000",
    "customs_name": "渗透剂",
    "components": "非离子表面活性剂68603-25-8 20%\n脂肪醇聚氧烷基醚68439-46-3 10%\n水 70%",
    "product_appearance": "无色至浅色透明液"
  },
  {
    "internal_code": "A-66B",
    "product_code": "3403910000",
    "customs_name": "皂洗剂",
    "components": "分散剂NNO9084-06-04 30%\n葡萄糖酸钠527-07-1 70%",
    "product_appearance": "浅黄色至黄色粉末"
  },
  {
    "internal_code": "A-66C",
    "product_code": "3403910000",
    "customs_name": "皂洗剂",
    "components": "分散剂NNO9084-06-04  50%\n葡萄糖酸钠527-07-1  50%",
    "product_appearance": "浅黄色至黄色粉末"
  },
  {
    "internal_code": "A-69",
    "product_code": "3403910000",
    "customs_name": "螯合分散剂",
    "components": "葡萄糖酸钠  15%\n元明粉  85%",
    "product_appearance": "白色粉末"
  },
  {
    "internal_code": "A-73",
    "product_code": "3402420000",
    "customs_name": "精练剂",
    "components": "非离子表面活性剂68603-25-8  15%\n脂肪醇聚氧烷基醚68439-46-3  10%\n水   75%",
    "product_appearance": "无色至泛白半透明液"
  },
  {
    "internal_code": "A-74F",
    "product_code": "3402420000",
    "customs_name": "除油剂",
    "components": "非离子表面活性剂68603-25-8 30%\n脂肪醇聚氧烷基醚68439-46-3  5%\n水 65%",
    "product_appearance": "浅黄色透明液"
  },
  {
    "internal_code": "A-79",
    "product_code": "3402420000",
    "customs_name": "非离子有机表面活性剂",
    "components": "非离子表面活性剂68603-25-8  20%\n脂肪醇聚氧烷基醚68439-46-3  20%\n水   60%",
    "product_appearance": "米白色乳液"
  },
  {
    "internal_code": "A-79AB",
    "product_code": "3402420000",
    "customs_name": "非离子有机表面活性剂",
    "components": "非离子表面活性剂68603-25-8 10%\n脂肪醇聚氧烷基醚68439-46-3  10%\n水 80%",
    "product_appearance": "米白色乳液"
  },
  {
    "internal_code": "A-79H",
    "product_code": "3402420000",
    "customs_name": "精练剂",
    "components": "非离子表面活性剂68603-25-8 45%\n脂肪醇聚氧烷基醚68439-46-3 15%\n水 40%",
    "product_appearance": "无色至浅黄色透明液"
  },
  {
    "internal_code": "A-85A",
    "product_code": "3402420000",
    "customs_name": "匀染剂",
    "components": "聚乙二醇 25322-68-3，  20%\n非离子表面活性剂68603-25-8 20%\n水  60%",
    "product_appearance": "黄色透明液"
  },
  {
    "internal_code": "A-85FC",
    "product_code": "3402420000",
    "customs_name": "匀染剂",
    "components": "聚乙二醇 25322-68-3， 35%\n非离子表面活性剂68603-25-8 35%\n水 30%",
    "product_appearance": "红棕色透明粘液"
  },
  {
    "internal_code": "A-85K",
    "product_code": "3402420000",
    "customs_name": "匀染剂",
    "components": "聚乙二醇 25322-68-3，  25%\n非离子表面活性剂68603-25-8 20%\n水 55%",
    "product_appearance": "黄色透明液(微朦）"
  },
  {
    "internal_code": "A-86",
    "product_code": "3402420000",
    "customs_name": "修补剂",
    "components": "乙二醇二醋酸酯111-55-7  45%\n非离子表面活性剂68603-25-8  55%",
    "product_appearance": "黄色透明液"
  },
  {
    "internal_code": "A-86A",
    "product_code": "3402420000",
    "customs_name": "修补剂",
    "components": "乙二醇二醋酸酯111-55-7  65%\n非离子表面活性剂68603-25-8  35%",
    "product_appearance": "黄色透明液"
  },
  {
    "internal_code": "A-86K",
    "product_code": "3402420000",
    "customs_name": "修补剂",
    "components": "乙二醇二醋酸酯111-55-7  25%\n非离子表面活性剂68603-25-8  75%",
    "product_appearance": "黄色透明液"
  },
  {
    "internal_code": "A-90C",
    "product_code": "3402420000",
    "customs_name": "精练剂",
    "components": "非离子表面活性剂68603-25-8 16%\n脂肪醇聚氧烷基醚68439-46-3 24%\n水 60%",
    "product_appearance": "无色至浅黄色透明液体"
  },
  {
    "internal_code": "A-90EA",
    "product_code": "3402420000",
    "customs_name": "除油剂",
    "components": "非离子表面活性剂68603-25-8 27%\n脂肪醇聚氧烷基醚68439-46-3  23%\n水  50%",
    "product_appearance": "无色透明液体"
  },
  {
    "internal_code": "A-90EB",
    "product_code": "3402420000",
    "customs_name": "除油剂",
    "components": "非离子表面活性剂68603-25-8  18%\n脂肪醇聚氧烷基醚68439-46-3  12%\n水  70%",
    "product_appearance": "无色透明液体"
  },
  {
    "internal_code": "A-90FC",
    "product_code": "3402420000",
    "customs_name": "除油剂",
    "components": "非离子表面活性剂68603-25-8 13%\n脂肪醇聚氧烷基醚68439-46-3 47%\n水 40%",
    "product_appearance": "浅黄透明液体"
  },
  {
    "internal_code": "A-90H",
    "product_code": "3402420000",
    "customs_name": "精练剂",
    "components": "非离子表面活性剂68603-25-8  60%\n脂肪醇聚氧烷基醚68439-46-3  20%\n水  20%",
    "product_appearance": "无色透明液体"
  },
  {
    "internal_code": "A-90HD",
    "product_code": "3402420000",
    "customs_name": "精练剂",
    "components": "非离子表面活性剂68603-25-8 45%\n脂肪醇聚氧烷基醚68439-46-3 15%\n水 40%",
    "product_appearance": "无色透明液体"
  },
  {
    "internal_code": "A-90HE",
    "product_code": "3402420000",
    "customs_name": "精练剂",
    "components": "非离子表面活性剂68603-25-8 35%\n脂肪醇聚氧烷基醚68439-46-3  15%\n水 50%",
    "product_appearance": "无色透明液体"
  },
  {
    "internal_code": "A-90K",
    "product_code": "3402420000",
    "customs_name": "除油剂",
    "components": "非离子表面活性剂68603-25-8 15%\n脂肪醇聚氧烷基醚68439-46-3  20%\n水  65%",
    "product_appearance": "无色透明液体"
  },
  {
    "internal_code": "A-90Y",
    "product_code": "3402420000",
    "customs_name": "非离子有机表面活性剂",
    "components": "非离子表面活性剂68603-25-8 15%\n脂肪醇聚氧烷基醚68439-46-3  25%\n水  60%",
    "product_appearance": "无色透明液体"
  },
  {
    "internal_code": "A-93B",
    "product_code": "3403910000",
    "customs_name": "渗透剂",
    "components": "柠檬酸  77-92-9  10%\n葡萄糖酸钠  41859-67-0  30%\n水  60%",
    "product_appearance": "无色透明液体"
  },
  {
    "internal_code": "B-3AB",
    "product_code": "3403910000",
    "customs_name": "纺织助剂消泡剂",
    "components": "端环氧硅油 9004-73-3：15%\n水：85%",
    "product_appearance": "白色粘稠液体"
  },
  {
    "internal_code": "B-3AC",
    "product_code": "3403910000",
    "customs_name": "纺织助剂消泡剂",
    "components": "端环氧硅油 9004-73-325%\n水：75%",
    "product_appearance": "白色粘稠液体"
  },
  {
    "internal_code": "B-4",
    "product_code": "2916150000",
    "customs_name": "抗黄变剂",
    "components": "油酸112-80-1 25%\n甘油56-81-5  25%\n水  50%",
    "product_appearance": "无色透明粘液"
  },
  {
    "internal_code": "B-65B",
    "product_code": "3403910000",
    "customs_name": "纺织助剂消泡剂",
    "components": "油酸112-80-1 35%\n甘油56-81-5  15%\n水 50%",
    "product_appearance": "无色至浅色半透明液"
  },
  {
    "internal_code": "B-76",
    "product_code": "3403910000",
    "customs_name": "纺织助剂整理剂",
    "components": "防水防油整理剂 CAS号：52591-27-2  25%\n山梨醇50-70-4  15%\n水 60%",
    "product_appearance": "乳白色液体"
  },
  {
    "internal_code": "B-9/CF1096",
    "product_code": "3402420000",
    "customs_name": "匀染剂",
    "components": "聚乙二醇 25322-68-3，:40%\n非离子表面活性剂68603-25-8:30%\n水： 30%",
    "product_appearance": "红棕色透明粘液"
  },
  {
    "internal_code": "B-9FB",
    "product_code": "3402420000",
    "customs_name": "匀染剂",
    "components": "聚乙二醇 25322-68-3， 20%\n非离子表面活性剂68603-25-8 10%\n水  70%",
    "product_appearance": "黄色透明粘液"
  },
  {
    "internal_code": "B-9HA",
    "product_code": "3402420000",
    "customs_name": "匀染剂",
    "components": "聚乙二醇 25322-68-3， 60%\n非离子表面活性剂68603-25-8 30%\n水 10%",
    "product_appearance": "黄色透明粘液"
  },
  {
    "internal_code": "B-9JD",
    "product_code": "3402420000",
    "customs_name": "匀染剂",
    "components": "聚乙二醇 25322-68-3， 10%\n非离子表面活性剂68603-25-8 5%\n水 85%",
    "product_appearance": "黄色透明粘液"
  },
  {
    "internal_code": "B-9MB",
    "product_code": "3402420000",
    "customs_name": "匀染剂",
    "components": "聚乙二醇 25322-68-3， 20%\n非离子表面活性剂68603-25-8 20%\n水  60%",
    "product_appearance": "黄色透明粘液"
  },
  {
    "internal_code": "B-9SB",
    "product_code": "3402420000",
    "customs_name": "匀染剂",
    "components": "聚乙二醇 25322-68-3， 15%\n非离子表面活性剂68603-25-8 15%\n水 70%",
    "product_appearance": "黄色透明粘液"
  },
  {
    "internal_code": "HM035",
    "product_code": "",
    "customs_name": "催化剂",
    "components": "氯化铵12125-02-9  50%\n工业盐7647-14-5  50%",
    "product_appearance": "绿色粉末"
  },
  {
    "internal_code": "HM053",
    "product_code": "2909499090",
    "customs_name": "修补剂",
    "components": "丙二醇苯醚  770-35-4   90%\n水  10%",
    "product_appearance": "无色透明液"
  },
  {
    "internal_code": "K112-LAW",
    "product_code": "2916150000",
    "customs_name": "抗静电剂",
    "components": "油酸112-80-1 35%\n甘油56-81-5  35%\n水 30%",
    "product_appearance": "黄色透明液"
  },
  {
    "internal_code": "K114-B",
    "product_code": "3402420000",
    "customs_name": "非离子有机表面活性剂",
    "components": "山梨醇50-70-4 35%\n甘油56-81-5  35%\n水  30%",
    "product_appearance": "无色透明液"
  },
  {
    "internal_code": "K117-B",
    "product_code": "3402420000",
    "customs_name": "非离子有机表面活性剂",
    "components": "油酸112-80-1  10%\n非离子表面活性剂68603-25-8 15%\n水  75%",
    "product_appearance": "近无色半透明粘液"
  },
  {
    "internal_code": "K123-G",
    "product_code": "3402420000",
    "customs_name": "非离子有机表面活性剂",
    "components": "非离子表面活性剂68603-25-8 40%\n脂肪醇聚氧烷基醚68439-46-3 30%\n水 30%",
    "product_appearance": "无色至微黄色透明液"
  },
  {
    "internal_code": "K123-GP",
    "product_code": "3402420000",
    "customs_name": "非离子有机表面活性剂",
    "components": "非离子表面活性剂68603-25-8 20%\n脂肪醇聚氧烷基醚68439-46-3 20%\n水 60%",
    "product_appearance": "无色透明液"
  },
  {
    "internal_code": "K129-H",
    "product_code": "3402420000",
    "customs_name": "非离子有机表面活性剂",
    "components": "油酸112-80-1 25%\n非离子表面活性剂68603-25-8 25%\n水 50%",
    "product_appearance": "黄色半透明粘液"
  },
  {
    "internal_code": "K132-D",
    "product_code": "3402420000",
    "customs_name": "非离子有机表面活性剂",
    "components": "油酸112-80-1 15%\n非离子表面活性剂68603-25-8 25%\n水 60%",
    "product_appearance": "浅黄色透明液"
  },
  {
    "internal_code": "K137",
    "product_code": "3402420000",
    "customs_name": "非离子有机表面活性剂",
    "components": "二乙二醇111-46-6  20%\n山梨醇50-70-4  15%\n水  65%",
    "product_appearance": "近无色透明粘液"
  },
  {
    "internal_code": "K143-D",
    "product_code": "3402420000",
    "customs_name": "非离子有机表面活性剂",
    "components": "乙二醇二醋酸酯111-55-7 50%\n非离子表面活性剂68603-25-8 50%",
    "product_appearance": "近无色透明粘液"
  },
  {
    "internal_code": "K15-S",
    "product_code": "3402420000",
    "customs_name": "匀染剂",
    "components": "非离子表面活性剂68603-25-8 35%\n脂肪醇聚氧烷基醚68439-46-3  35%\n水 30%",
    "product_appearance": "黄色透明粘液"
  },
  {
    "internal_code": "K15-SB",
    "product_code": "3402420000",
    "customs_name": "匀染剂",
    "components": "非离子表面活性剂68603-25-8 25%\n脂肪醇聚氧烷基醚68439-46-3 15%\n水 60%",
    "product_appearance": "黄色透明液"
  },
  {
    "internal_code": "K15-SK",
    "product_code": "3402420000",
    "customs_name": "匀染剂",
    "components": "非离子表面活性剂68603-25-8 10%\n脂肪醇聚氧烷基醚68439-46-3  25%\n水 65%",
    "product_appearance": "黄色透明液"
  },
  {
    "internal_code": "K15-SP",
    "product_code": "3402420000",
    "customs_name": "匀染剂",
    "components": "非离子表面活性剂68603-25-8 35%\n脂肪醇聚氧烷基醚68439-46-3  45%\n水 20%",
    "product_appearance": "黄色透明粘液"
  },
  {
    "internal_code": "K15-WHC",
    "product_code": "3402420000",
    "customs_name": "匀染剂",
    "components": "非离子表面活性剂68603-25-8 15%\n脂肪醇聚氧烷基醚68439-46-3  40%\n水 45%",
    "product_appearance": "棕黄色透明液体"
  },
  {
    "internal_code": "K169-G",
    "product_code": "3402420000",
    "customs_name": "非离子有机表面活性剂",
    "components": "非离子表面活性剂68603-25-8 25%\n脂肪醇聚氧烷基醚68439-46-3  35%\n水 40%",
    "product_appearance": "无色至浅色透明液"
  },
  {
    "internal_code": "K169-GB",
    "product_code": "3402420000",
    "customs_name": "非离子有机表面活性剂",
    "components": "非离子表面活性剂68603-25-8 15%\n脂肪醇聚氧烷基醚68439-46-3  15%\n水 70%",
    "product_appearance": "无色透明液"
  },
  {
    "internal_code": "K176",
    "product_code": "3402420000",
    "customs_name": "非离子有机表面活性剂",
    "components": "油酸112-80-1\n非离子表面活性剂68603-25-8",
    "product_appearance": "黄色透明液"
  },
  {
    "internal_code": "K187-C",
    "product_code": "3402420000",
    "customs_name": "非离子有机表面活性剂",
    "components": "油酸112-80-1 20%\n非离子表面活性剂68603-25-8 20%\n水 60%",
    "product_appearance": "无色透明液"
  },
  {
    "internal_code": "K191-C",
    "product_code": "3402420000",
    "customs_name": "非离子有机表面活性剂",
    "components": "油酸112-80-1 35%\n非离子表面活性剂68603-25-8 20%\n水 45%",
    "product_appearance": "浅黄至黄色透明液"
  },
  {
    "internal_code": "K191-H",
    "product_code": "3402420000",
    "customs_name": "非离子有机表面活性剂",
    "components": "油酸112-80-1 25%\n非离子表面活性剂68603-25-8 20%\n水 55%",
    "product_appearance": "浅黄至黄色透明液"
  },
  {
    "internal_code": "K194-C",
    "product_code": "3402420000",
    "customs_name": "匀染剂",
    "components": "非离子表面活性剂68603-25-8 55%\n脂肪醇聚氧烷基醚68439-46-3  15%\n水 30%",
    "product_appearance": "深黄色透明液"
  },
  {
    "internal_code": "K194-CE",
    "product_code": "3402420000",
    "customs_name": "匀染剂",
    "components": "非离子表面活性剂68603-25-8 35%\n脂肪醇聚氧烷基醚68439-46-3  45%\n水 20%",
    "product_appearance": "黄色透明液"
  },
  {
    "internal_code": "K200-E",
    "product_code": "3403910000",
    "customs_name": "纺织助剂整理剂",
    "components": "纯碱497-19-8 10%\n三聚磷酸钠7758-29-4  90%",
    "product_appearance": "白色粉状"
  },
  {
    "internal_code": "K200-K",
    "product_code": "3403910000",
    "customs_name": "纺织助剂整理剂",
    "components": "纯碱497-19-8 20%\n三聚磷酸钠7758-29-4 80%",
    "product_appearance": "白色粉状"
  },
  {
    "internal_code": "K218",
    "product_code": "3402420000",
    "customs_name": "非离子有机表面活性剂",
    "components": "聚乙二醇 25322-68-3， 10%\n非离子表面活性剂68603-25-8 30%\n水 60%",
    "product_appearance": "米黄色液体"
  },
  {
    "internal_code": "K218-D",
    "product_code": "3402420000",
    "customs_name": "非离子有机表面活性剂",
    "components": "聚乙二醇 25322-68-3， 10%\n非离子表面活性剂68603-25-8 10%\n水 80%",
    "product_appearance": "米黄色液体"
  },
  {
    "internal_code": "K22-L",
    "product_code": "3403910000",
    "customs_name": "匀染剂",
    "components": "分散剂NNO9084-06-04 30%\n葡萄糖酸钠527-07-1 30%\n水 40%",
    "product_appearance": "棕黑色液体"
  },
  {
    "internal_code": "K22-LA",
    "product_code": "3403910000",
    "customs_name": "匀染剂",
    "components": "分散剂NNO9084-06-04 20%\n葡萄糖酸钠527-07-1 20%\n水 60%",
    "product_appearance": "棕黑色液体"
  },
  {
    "internal_code": "K22-LM",
    "product_code": "3403910000",
    "customs_name": "匀染剂",
    "components": "分散剂NNO9084-06-04 15%\n葡萄糖酸钠527-07-1 15%\n水 70%",
    "product_appearance": "棕黑色液体"
  },
  {
    "internal_code": "K242-D",
    "product_code": "2916150000",
    "customs_name": "抗黄变剂",
    "components": "油酸112-80-1 10%\n甘油56-81-5  40%\n水  50%",
    "product_appearance": "无色至浅色透明液"
  },
  {
    "internal_code": "K242-F",
    "product_code": "3403910000",
    "customs_name": "纺织助剂整理剂",
    "components": "油酸112-80-1 15%\n甘油56-81-5  25%\n水  60%",
    "product_appearance": "白色粉状"
  },
  {
    "internal_code": "K25",
    "product_code": "3402420000",
    "customs_name": "非离子有机表面活性剂",
    "components": "聚乙二醇 25322-68-3， 10%\n非离子表面活性剂68603-25-8 5%\n水 85%",
    "product_appearance": "无色透明粘液"
  },
  {
    "internal_code": "K25-B",
    "product_code": "3402420000",
    "customs_name": "非离子有机表面活性剂",
    "components": "聚乙二醇 25322-68-3， 5%\n非离子表面活性剂68603-25-8 5%\n水 90%",
    "product_appearance": "无色透明粘液"
  },
  {
    "internal_code": "K25-AD",
    "product_code": "3402420000",
    "customs_name": "非离子有机表面活性剂",
    "components": "聚乙二醇 25322-68-3， 5%\n非离子表面活性剂68603-25-8 5%\n水 90%",
    "product_appearance": "无色透明粘液"
  },
  {
    "internal_code": "K2-GB",
    "product_code": "2942000000",
    "customs_name": "螯合分散剂",
    "components": "三聚磷酸钠7758-29-4 40%\n葡萄糖酸钠527-07-1  10%\n水 50%",
    "product_appearance": "无色透明液"
  },
  {
    "internal_code": "K33-GB",
    "product_code": "3403910000",
    "customs_name": "纺织助剂整理剂",
    "components": "纯碱497-19-8 15%\n元明粉7757-82-6  85%",
    "product_appearance": "白色粉状"
  },
  {
    "internal_code": "K42-P",
    "product_code": "3402420000",
    "customs_name": "非离子有机表面活性剂",
    "components": "非离子表面活性剂68603-25-8 15%\n脂肪醇聚氧烷基醚68439-46-3  40%\n水 45%",
    "product_appearance": "浅黄至黄色粘液"
  },
  {
    "internal_code": "K50-G",
    "product_code": "3402420000",
    "customs_name": "非离子有机表面活性剂",
    "components": "非离子表面活性剂68603-25-8 45%\n脂肪醇聚氧烷基醚68439-46-3  5%\n水 50%",
    "product_appearance": "黄色透明粘液"
  },
  {
    "internal_code": "K6-A",
    "product_code": "2942000000",
    "customs_name": "皂洗剂",
    "components": "聚合物PMA-60: 26677-99-6   60%\n水 40%",
    "product_appearance": "无色至浅黄色透明液"
  },
  {
    "internal_code": "K6-AY",
    "product_code": "2942000000",
    "customs_name": "皂洗剂",
    "components": "聚合物PMA-60:26677-99-6  50%\n水 50%",
    "product_appearance": "深黄色透明液"
  },
  {
    "internal_code": "K25-E",
    "product_code": "3403910000",
    "customs_name": "还原清洗剂",
    "components": "碳酸钠 50%，葡萄糖酸钠40%，元明粉10%，",
    "product_appearance": "白色粉状"
  },
  {
    "internal_code": "K77-071",
    "product_code": "3403910000",
    "customs_name": "还原清洗剂",
    "components": "酸钠 50%，葡萄糖酸钠40%，元明粉10%，",
    "product_appearance": "白色粉状"
  },
  {
    "internal_code": "K77-082",
    "product_code": "3403910000",
    "customs_name": "还原清洗剂",
    "components": "碳酸钠 50%，葡萄糖酸钠40%，元明粉10%，",
    "product_appearance": "白色粉状"
  },
  {
    "internal_code": "K7-E",
    "product_code": "3403910000",
    "customs_name": "还原清洗剂",
    "components": "三聚磷酸钠7758-29-4 50%\n葡萄糖酸钠527-07-1  50%",
    "product_appearance": "白色粉状"
  },
  {
    "internal_code": "K83-PC",
    "product_code": "3402420000",
    "customs_name": "非离子有机表面活性剂",
    "components": "非离子表面活性剂68603-25-8 25%\n脂肪醇聚氧烷基醚68439-46-3  45%\n水 30%",
    "product_appearance": "白色或微黄色膏状体"
  },
  {
    "internal_code": "K8-D",
    "product_code": "3403910000",
    "customs_name": "还原清洗剂",
    "components": "碳酸钠 50%，葡萄糖酸钠40%，元明粉10%，",
    "product_appearance": "白色粉状"
  },
  {
    "internal_code": "K8-DE",
    "product_code": "3403910000",
    "customs_name": "还原清洗剂",
    "components": "碳酸钠 50%，葡萄糖酸钠40%，元明粉10%，",
    "product_appearance": "白色粉状"
  },
  {
    "internal_code": "K94",
    "product_code": "3403910000",
    "customs_name": "螯合分散剂",
    "components": "纯碱 30%、三聚磷酸钠 50%、元明粉 20%",
    "product_appearance": "白色粉状"
  },
  {
    "internal_code": "M1-10",
    "product_code": "3507909090",
    "customs_name": "酶制剂",
    "components": "纤维素酶9012-54-8 30%\n山梨醇50-70-4  10%\n水 60%",
    "product_appearance": "黄棕色液体"
  },
  {
    "internal_code": "M7-5",
    "product_code": "3507909090",
    "customs_name": "酶制剂",
    "components": "纤维素酶9012-54-8  25%\n葡萄糖50-99-7  75%",
    "product_appearance": "黄色粉状"
  },
  {
    "internal_code": "M7-6",
    "product_code": "3507909090",
    "customs_name": "酶制剂",
    "components": "纤维素酶9012-54-8  45%\n葡萄糖50-99-7  55%",
    "product_appearance": "黄色粉状"
  },
  {
    "internal_code": "CF539",
    "product_code": "3507909090",
    "customs_name": "酶制剂",
    "components": "纤维素酶  9012-54-8   50%   水 50%",
    "product_appearance": "深棕色透明液"
  },
  {
    "internal_code": "CF781",
    "product_code": "3403910000",
    "customs_name": "纺织助剂整理剂",
    "components": "葡萄糖酸钠 527-07-1    30%     葡萄糖  50-99-7  20%  水50%",
    "product_appearance": "泛白半透至透明粘液"
  },
  {
    "internal_code": "CF050B",
    "product_code": "3403910000",
    "customs_name": "皂洗剂",
    "components": "聚合物PMA-60    26677-99-6   30%    水  70%",
    "product_appearance": "无色透明液"
  },
  {
    "internal_code": "T21",
    "product_code": "3402420000",
    "customs_name": "非离子有机表面活性剂",
    "components": "油酸112-80-1 35%\n非离子表面活性剂68603-25-8 10%\n水 55%",
    "product_appearance": "米白色液体"
  },
  {
    "internal_code": "T2-D",
    "product_code": "3403910000",
    "customs_name": "皂洗剂",
    "components": "三聚磷酸钠7758-29-4  30%\n葡萄糖酸钠527-07-1  10%\n水 60%",
    "product_appearance": "无色透明粘液"
  },
  {
    "internal_code": "T65",
    "product_code": "3402420000",
    "customs_name": "非离子有机表面活性剂",
    "components": "非离子表面活性剂68603-25-8 28%\n脂肪醇聚氧烷基醚68439-46-3 32%\n水  40%",
    "product_appearance": "无色透明粘液"
  },
  {
    "internal_code": "H-1C",
    "product_code": "3402420000",
    "customs_name": "非离子有机表面活性剂",
    "components": "非离子表面活性剂68603-25-8:35%\n脂肪醇聚氧烷基醚68439-46-3:65%",
    "product_appearance": "淡黄色液体"
  },
  {
    "internal_code": "K18",
    "product_code": "3403910000",
    "customs_name": "纺织助剂整理剂",
    "components": "葡萄糖酸钠  50%\n元明粉   50%",
    "product_appearance": "白色粉末"
  },
  {
    "internal_code": "B-72B",
    "product_code": "3403910000",
    "customs_name": "纺织助剂湿摩擦牢度提升剂",
    "components": "水性聚氨酯30%，水70%",
    "product_appearance": "浅黄色至黄色透明粘液（久置色深）"
  },
  {
    "internal_code": "B-25B",
    "product_code": "3403910000",
    "customs_name": "纺织助剂湿摩擦牢度提升剂",
    "components": "水性聚氨酯30%，水70%",
    "product_appearance": "浅黄色至黄色透明粘液（久置色深）"
  },
  {
    "internal_code": "B-12F",
    "product_code": "3403910000",
    "customs_name": "纺织助剂湿摩擦牢度提升剂",
    "components": "水性聚氨酯30%，水70%",
    "product_appearance": "浅黄色至黄色透明粘液（久置色深）"
  },
  {
    "internal_code": "B-12FH",
    "product_code": "3403910000",
    "customs_name": "纺织助剂湿摩擦牢度提升剂",
    "components": "水性聚氨酯30%，水70%",
    "product_appearance": "浅黄色至黄色透明粘液（久置色深）"
  },
  {
    "internal_code": "K255-BA",
    "product_code": "3403910000",
    "customs_name": "纺织助剂湿摩擦牢度提升剂",
    "components": "水性聚氨酯30%，水70%",
    "product_appearance": "浅黄色至黄色透明粘液（久置色深）"
  },
  {
    "internal_code": "B-68Y",
    "product_code": "3403910000",
    "customs_name": "纺织助剂湿摩擦牢度提升剂",
    "components": "水性聚氨酯30%，水70%",
    "product_appearance": "浅黄色至黄色透明粘液（久置色深）"
  },
  {
    "internal_code": "B-69H",
    "product_code": "3403910000",
    "customs_name": "纺织助剂湿摩擦牢度提升剂",
    "components": "水性聚氨酯30%，水70%",
    "product_appearance": "浅黄色至黄色透明粘液（久置色深）"
  },
  {
    "internal_code": "B-68D",
    "product_code": "3403910000",
    "customs_name": "纺织助剂湿摩擦牢度提升剂",
    "components": "水性聚氨酯30%，水70%",
    "product_appearance": "浅黄色至黄色透明粘液（久置色深）"
  },
  {
    "internal_code": "B-12D",
    "product_code": "3403910000",
    "customs_name": "纺织助剂湿摩擦牢度提升剂",
    "components": "水性聚氨酯30%，水70%",
    "product_appearance": "浅黄色至黄色透明粘液（久置色深）"
  },
  {
    "internal_code": "CF929",
    "product_code": "3403910000",
    "customs_name": "纺织助剂整理剂",
    "components": "聚乙烯醇，9002-89-5 94%  元明粉  7757-82-6   6%",
    "product_appearance": "白色粉末"
  },
  {
    "internal_code": "B-25Q",
    "product_code": "3403910000",
    "customs_name": "纺织助剂湿摩擦牢度提升剂",
    "components": "水性聚氨酯30%，水70%",
    "product_appearance": "浅黄色至黄色透明粘液（久置色深）"
  },
  {
    "internal_code": "K168-D",
    "product_code": "3403910000",
    "customs_name": "纺织助剂湿摩擦牢度提升剂",
    "components": "水性聚氨酯30%，水70%",
    "product_appearance": "浅黄色至黄色透明粘液（久置色深）"
  },
  {
    "internal_code": "B-12B",
    "product_code": "3403910000",
    "customs_name": "纺织助剂湿摩擦牢度提升剂",
    "components": "水性聚氨酯30%，水70%",
    "product_appearance": "浅黄色至黄色透明粘液（久置色深）"
  },
  {
    "internal_code": "K255-BAH",
    "product_code": "3403910000",
    "customs_name": "纺织助剂湿摩擦牢度提升剂",
    "components": "水性聚氨酯30%，水70%",
    "product_appearance": "浅黄色至黄色透明粘液（久置色深）"
  },
  {
    "internal_code": "CF253E（宏昊）",
    "product_code": "3403910000",
    "customs_name": "还原清洗剂",
    "components": "元明粉 50%，葡萄糖酸钠 25%，碳酸钠 25%",
    "product_appearance": "白色粉末"
  },
  {
    "internal_code": "CF284",
    "product_code": "3403910000",
    "customs_name": "皂洗剂",
    "components": "元明粉 30%，葡萄糖酸钠 45%，碳酸钠 25%",
    "product_appearance": "白色粉末"
  },
  {
    "internal_code": "CF073",
    "product_code": "34039100000",
    "customs_name": "纺织助剂整理剂",
    "components": "葡萄糖酸钠  527-07-1  60%；\n元明粉  7757-82-6   40%",
    "product_appearance": "白色粉末"
  },
  {
    "internal_code": "CP89",
    "product_code": "34039100000",
    "customs_name": "阻燃剂",
    "components": "阻燃剂  20120-33-6   90%\n水  10%",
    "product_appearance": "无色透明液体"
  },
  {
    "internal_code": "CF793",
    "product_code": "34039100000",
    "customs_name": "阻燃剂",
    "components": "阻燃剂  20120-33-6   80%\n水  20%",
    "product_appearance": "无色透明液体"
  },
  {
    "internal_code": "T25-B",
    "product_code": "3402420000",
    "customs_name": "非离子有机表面活性剂",
    "components": "非离子表面活性剂68603-25-8   35%\n脂肪醇聚氧烷基醚68439-46-3    45%\n水   20%",
    "product_appearance": "黄色糊状"
  },
  {
    "internal_code": "CF068RA",
    "product_code": "3403910000",
    "customs_name": "匀染剂",
    "components": "分散剂NNO9084-06-04 80%\n元明粉7757-82-6  20%",
    "product_appearance": "黄色粉末"
  },
  {
    "internal_code": "CF021B",
    "product_code": "3403910000",
    "customs_name": "纺织助剂整理剂",
    "components": "葡萄糖酸钠527-07-1 85%\n元明粉c  15%",
    "product_appearance": "白色至浅黄色粉末"
  },
  {
    "internal_code": "CF366B",
    "product_code": "2942000000",
    "customs_name": "螯合分散剂",
    "components": "HEDP 2809-21-4  30%\n葡萄糖酸钠527-07-1 25%\n水   45%",
    "product_appearance": "深黄色透明液"
  },
  {
    "internal_code": "GW96-01",
    "product_code": "3402410000",
    "customs_name": "固色剂",
    "components": "水：7732-18-5，55%\n二甲基二烯丙基氯化铵：26062-79-3，45%",
    "product_appearance": "微黄色透明粘液"
  },
  {
    "internal_code": "A-44",
    "product_code": "3403910000",
    "customs_name": "蜡乳液",
    "components": "石蜡：8002-72-2 14%\n吐温：9005-67-8  6%\n水： 7732-18-5：  80%",
    "product_appearance": "乳白色液体"
  },
  {
    "internal_code": "T152",
    "product_code": "3402900000",
    "customs_name": "固色剂",
    "components": "十二烷基苯磺酸钠：25155-30-0，40%\n分散剂：26545-58-4，5%\n水：7732-18-5，55%",
    "product_appearance": "棕黑色透明液"
  },
  {
    "internal_code": "GS26-01C",
    "product_code": "3402900000",
    "customs_name": "固色剂",
    "components": "双酚S：80-09-1，55%\n水：7732-18-5，45%",
    "product_appearance": "棕黑色透明液"
  },
  {
    "internal_code": "CF1135",
    "product_code": "3402900000",
    "customs_name": "固色剂",
    "components": "十二烷基苯磺酸钠：25155-30-0，30%\n硫代硫酸钠：7772-98-7，10%\n水：7732-18-5，60%",
    "product_appearance": "无色透明液"
  },
  {
    "internal_code": "CF1050",
    "product_code": "3403910000",
    "customs_name": "纺织助剂防染剂",
    "components": "聚乙二醇50%，脂肪醇聚氧乙烯醚40%，水10%",
    "product_appearance": "黄色半透明液"
  },
  {
    "internal_code": "XY-789",
    "product_code": "3403910000",
    "customs_name": "纺织助剂稳定剂",
    "components": "葡萄糖酸钠527-07-1  15%\n元明粉7757-82-6 15%\n水 70%",
    "product_appearance": "无色透明液"
  },
  {
    "internal_code": "CF526E",
    "product_code": "3507909090",
    "customs_name": "酶制剂",
    "components": "纤维素酶9012-54-8 80%  元明粉 20%",
    "product_appearance": "黄色颗粒"
  },
  {
    "internal_code": "CF526C",
    "product_code": "3507909090",
    "customs_name": "酶制剂",
    "components": "纤维素酶9012-54-8 70%   元明粉 30%",
    "product_appearance": "黄色粉末"
  },
  {
    "internal_code": "XY-869",
    "product_code": "3402420000",
    "customs_name": "匀染剂",
    "components": "聚乙二醇 25322-68-3，:40%\n非离子表面活性剂68603-25-8:30%\n水： 30%",
    "product_appearance": "棕黄色透明液（朦）"
  },
  {
    "internal_code": "CF028",
    "product_code": "3402420000",
    "customs_name": "渗透剂",
    "components": "非离子表面活性剂68603-25-8 40%\n脂肪醇聚氧烷基醚68439-46-3 40%\n水 20%",
    "product_appearance": "无色透明液"
  },
  {
    "internal_code": "CF817F",
    "product_code": "3403910000",
    "customs_name": "纺织助剂防染粉",
    "components": "脂肪醇聚氧烷基醚68439-46-3  55%\n葡萄糖酸钠527-07-1 45%",
    "product_appearance": "白色粉末"
  },
  {
    "internal_code": "K3-L",
    "product_code": "3402420000",
    "customs_name": "渗透剂",
    "components": "非离子表面活性剂68603-25-8 10%\n脂肪醇聚氧烷基醚68439-46-3 5%\n水 85%",
    "product_appearance": "带蓝光透明粘液"
  },
  {
    "internal_code": "CF033（博斯汇出）",
    "product_code": "2839110000",
    "customs_name": "偏硅酸钠",
    "components": "偏硅酸钠：100%",
    "product_appearance": "白色颗粒"
  },
  {
    "internal_code": "T153",
    "product_code": "3402900000",
    "customs_name": "固色剂",
    "components": "酚醛树脂：9003-35-4：27%\n分散剂：26545-58-4；10%  \n柠檬酸钠：68-04-2：3%\n水：7732-18-5，60%",
    "product_appearance": "黄色透明液"
  },
  {
    "internal_code": "K151-G",
    "product_code": "3403910000",
    "customs_name": "吸湿排汗整理剂",
    "components": "端环氧硅油 9004-73-3  15%\n吸湿排汗整理剂9016-88-0   10%\n水  75%",
    "product_appearance": "乳白色不透明液"
  },
  {
    "internal_code": "F-182B",
    "product_code": "3403910000",
    "customs_name": "纺织柔软剂",
    "components": "聚醚环氧硅油9004-73-3：25％+水：75％",
    "product_appearance": "无色透明液体"
  },
  {
    "internal_code": "K24",
    "product_code": "3402420000",
    "customs_name": "渗透剂",
    "components": "聚乙二醇单油酸酯9004-96-0 35%\n非离子表面活性剂68603-25-8 55%\n水 10%",
    "product_appearance": "无色透明液"
  },
  {
    "internal_code": "A-77Y",
    "product_code": "3402420000",
    "customs_name": "渗透剂",
    "components": "非离子表面活性剂68603-25-8  50%\n脂肪醇聚氧烷基醚68439-46-3  20%\n柠檬酸77-92-9  5%\n水 20%",
    "product_appearance": "黄色透明液(微朦）"
  },
  {
    "internal_code": "CF538D",
    "product_code": "3507909090",
    "customs_name": "酶制剂",
    "components": "纤维素酶9012-54-8 75%\n山梨醇50-70-4  15%\n水 10%",
    "product_appearance": "墨绿色透明液"
  },
  {
    "internal_code": "F-161",
    "product_code": "3403910000",
    "customs_name": "纺织柔软剂",
    "components": "聚二甲基硅氧烷（硅油）50%  9016-00-6，非离子乳化剂 10% 68213-23-0，水 40% 7732-18-5",
    "product_appearance": "黄色透明液体"
  },
  {
    "internal_code": "K13-Y",
    "product_code": "3402900000",
    "customs_name": "固色剂",
    "components": "双酚S：80-09-1；55%\n水：7732-18-5；45%",
    "product_appearance": "棕黑色透明液体"
  },
  {
    "internal_code": "CF1108/CF1104B",
    "product_code": "3403910000",
    "customs_name": "纺织助剂整理剂",
    "components": "荧光增白剂    80%\n元明粉 20%",
    "product_appearance": "黄绿色粉末"
  },
  {
    "internal_code": "CF1104D",
    "product_code": "3403910000",
    "customs_name": "纺织助剂整理剂",
    "components": "荧光增白剂   60%\n水 40%",
    "product_appearance": "棕黑色液体"
  },
  {
    "internal_code": "B-90PCA",
    "product_code": "3402410000",
    "customs_name": "固色剂",
    "components": "水：7732-18-5，70%\n二甲基二烯丙基氯化铵：26062-79-3，30%",
    "product_appearance": "黄色透明液"
  },
  {
    "internal_code": "K6-AS",
    "product_code": "2942000000",
    "customs_name": "皂洗剂",
    "components": "聚合物PMA-60: 26677-99-6   60%\n水 40%",
    "product_appearance": "无色至黄色液体"
  },
  {
    "internal_code": "T73-G",
    "product_code": "2921290090",
    "customs_name": "固色剂",
    "components": "N,N,N',N',N'-五(2-羟丙基)二乙三胺：17121-34-5，30%\n水：7732-18-5，70%  ( 属于A+B=C类情况，附加工艺单）",
    "product_appearance": "黄色透明液"
  },
  {
    "internal_code": "CF004E",
    "product_code": "3402420000",
    "customs_name": "非离子有机表面活性剂",
    "components": "脂肪醇聚氧乙烯醚   95%\n水 5%",
    "product_appearance": "无色液体（低温结块）"
  },
  {
    "internal_code": "CF772",
    "product_code": "3402420000",
    "customs_name": "非离子有机表面活性剂",
    "components": "脂肪醇聚氧乙烯醚   95%\n水 5%",
    "product_appearance": "无色透明液体"
  },
  {
    "internal_code": "F-369-9(8916)",
    "product_code": "3403910000",
    "customs_name": "纺织柔软剂",
    "components": "聚二甲基硅氧烷（硅油）50%  9016-00-6，非离子乳化剂 10% 68213-23-0，水 40% 7732-18-5",
    "product_appearance": "黄色液体"
  },
  {
    "internal_code": "F-152-6(8990A)",
    "product_code": "3403910000",
    "customs_name": "纺织柔软剂",
    "components": "聚二甲基硅氧烷（硅油）50%  9016-00-6，非离子乳化剂 10% 68213-23-0，水 40% 7732-18-5",
    "product_appearance": "黄色液体"
  },
  {
    "internal_code": "B-24",
    "product_code": "3403910000",
    "customs_name": "纺织助剂稳定剂",
    "components": "葡萄糖  50-99-7  10%\n水  90%",
    "product_appearance": "棕黑色透明液"
  },
  {
    "internal_code": "K11-GA",
    "product_code": "3402420000",
    "customs_name": "非离子有机表面活性剂",
    "components": "乙二醇二醋酸酯111-55-7  65%\n非离子表面活性剂68603-25-8  25%\n水  10%",
    "product_appearance": "黄色透明液体(久置变深）"
  },
  {
    "internal_code": "GW95-04",
    "product_code": "3402410000",
    "customs_name": "固色剂",
    "components": "水：7732-18-5，49%\n二甲基二烯丙基氯化铵：26062-79-3，51%",
    "product_appearance": "黄色微朦粘液"
  },
  {
    "internal_code": "F54",
    "product_code": "3402420000",
    "customs_name": "渗透剂",
    "components": "非离子表面活性剂68603-25-8 8%\n脂肪醇聚氧烷基醚68439-46-3  10%\n水 72%",
    "product_appearance": "乳白色带蓝光乳液"
  },
  {
    "internal_code": "HM052A",
    "product_code": "3403910000",
    "customs_name": "纺织助剂整理剂",
    "components": "杀菌剂   32426-10-1   50%\n水  50%",
    "product_appearance": "无色透明液"
  },
  {
    "internal_code": "CF1136",
    "product_code": "3402420000",
    "customs_name": "纺织助剂整理剂",
    "components": "非离子表面活性剂68603-25-8:40%\n水  60%",
    "product_appearance": "白色液体"
  },
  {
    "internal_code": "LB-132D-2",
    "product_code": "3403910000",
    "customs_name": "纺织柔软剂",
    "components": "聚二甲基硅氧烷（硅油）50%  9016-00-6，非离子乳化剂 10% 68213-23-0，水 40% 7732-18-5",
    "product_appearance": "浅黄色透明液体（久置会变黄）"
  },
  {
    "internal_code": "A-60F",
    "product_code": "3402420000",
    "customs_name": "渗透剂",
    "components": "",
    "product_appearance": "无色至浅色透明液"
  },
  {
    "internal_code": "K22-LD",
    "product_code": "3403910000",
    "customs_name": "匀染剂",
    "components": "分散剂NNO9084-06-04 25%\n葡萄糖酸钠527-07-1 20%\n水 55%",
    "product_appearance": "棕黄色透明液"
  },
  {
    "internal_code": "K6-ABC",
    "product_code": "2942000000",
    "customs_name": "皂洗剂",
    "components": "聚合物PMA-60  26677-99-6 33%\n水 67%",
    "product_appearance": "浅黄色透明液"
  },
  {
    "internal_code": "T16-HM",
    "product_code": "2921290090",
    "customs_name": "固色剂",
    "components": "二甘醇：111-46-6，9%\n甘油：56-81-5，24%\n水：7732-18-5，65%",
    "product_appearance": "黄色透明微粘液"
  },
  {
    "internal_code": "A-90JA",
    "product_code": "3402420000",
    "customs_name": "非离子有机表面活性剂",
    "components": "非离子表面活性剂68603-25-8  52%\n脂肪醇聚氧烷基醚68439-46-3  23%\n水 25%",
    "product_appearance": "无色至浅色透明液"
  },
  {
    "internal_code": "CF1151",
    "product_code": "3402420000",
    "customs_name": "非离子有机表面活性剂",
    "components": "非离子表面活性剂68603-25-8  45%\n脂肪醇聚氧烷基醚68439-46-3  50%\n水 5%",
    "product_appearance": "黄色透明液"
  },
  {
    "internal_code": "CF793A",
    "product_code": "34039100000",
    "customs_name": "阻燃剂",
    "components": "阻燃剂   14657-64-8  80%\n水  20%",
    "product_appearance": "无色透明液体"
  },
  {
    "internal_code": "CF842A",
    "product_code": "3403910000",
    "customs_name": "防水剂",
    "components": "防水剂  65605-70-1 30%\n山梨醇  608-66-2  20%\n水     50%",
    "product_appearance": "乳白色液体"
  },
  {
    "internal_code": "A-93A",
    "product_code": "3403910000",
    "customs_name": "纺织助剂缓冲剂",
    "components": "柠檬酸  77-92-9  10%\n葡萄糖酸钠  41859-67-0  30%\n水  60%",
    "product_appearance": "无色透明液"
  },
  {
    "internal_code": "CF539A",
    "product_code": "3507909090",
    "customs_name": "酶制剂",
    "components": "纤维素酶  9012-54-8   50%   水 50%",
    "product_appearance": "深棕色透明液"
  },
  {
    "internal_code": "T153B",
    "product_code": "3402900000",
    "customs_name": "固色剂",
    "components": "酚醛树脂：9003-35-4：27%\n分散剂：26545-58-4；10%  \n柠檬酸钠：68-04-2：3%\n水：7732-18-5，60%",
    "product_appearance": "黄色透明液"
  },
  {
    "internal_code": "B-73N",
    "product_code": "3403910000",
    "customs_name": "纺织助剂整理剂",
    "components": "防水防油整理剂    17527-29-6   50%\n水   50%",
    "product_appearance": "乳白色液体"
  },
  {
    "internal_code": "B-75G",
    "product_code": "3403910000",
    "customs_name": "纺织助剂整理剂",
    "components": "交联剂：9009-54-5  60%\n水   40%",
    "product_appearance": "乳白色液体"
  },
  {
    "internal_code": "CF943B",
    "product_code": "3403910000",
    "customs_name": "防水剂",
    "components": "无氟防水剂   9009-54-5  70%\n水  30%",
    "product_appearance": "乳白不透明液体"
  },
  {
    "internal_code": "CF849D / CF849H",
    "product_code": "3403910000",
    "customs_name": "防水剂",
    "components": "防水剂  65605-70-1  80%\n水  20%",
    "product_appearance": "乳白偏黄液体"
  },
  {
    "internal_code": "CF524C",
    "product_code": "3507909090",
    "customs_name": "酶制剂",
    "components": "纤维素酶9012-54-8 70%\n山梨醇50-70-4  10%\n水 20%",
    "product_appearance": "深棕色透明液体"
  },
  {
    "internal_code": "F-161F",
    "product_code": "3403910000",
    "customs_name": "纺织柔软剂",
    "components": "聚二甲基硅氧烷（硅油）50%  9016-00-6，非离子乳化剂 10% 68213-23-0，水 40% 7732-18-5",
    "product_appearance": "浅黄色透明粘液"
  },
  {
    "internal_code": "F-399H-2",
    "product_code": "3403910000",
    "customs_name": "纺织柔软剂",
    "components": "聚二甲基硅氧烷（硅油）50%  9016-00-6，非离子乳化剂 10% 68213-23-0，水 40% 7732-18-5",
    "product_appearance": "无色至浅黄色透明液体"
  },
  {
    "internal_code": "GY-794",
    "product_code": "3403910000",
    "customs_name": "纺织柔软剂",
    "components": "聚二甲基硅氧烷（硅油）50%  9016-00-6，非离子乳化剂 10% 68213-23-0，水 40% 7732-18-5",
    "product_appearance": "无色至浅黄色透明液体"
  },
  {
    "internal_code": "K6-F",
    "product_code": "2942000000",
    "customs_name": "皂洗剂",
    "components": "聚合物PMA-60 26677-99-6 70%\n水 30%",
    "product_appearance": "浅黄色至黄色透明液"
  },
  {
    "internal_code": "B-27",
    "product_code": "3402900000",
    "customs_name": "固色剂",
    "components": "双酚S：80-09-1；55%\n水：7732-18-5；45%",
    "product_appearance": "棕黑色液体"
  },
  {
    "internal_code": "CF388B",
    "product_code": "3402420000",
    "customs_name": "消泡剂",
    "components": "消泡剂 27306-78-1；20%\n水； 80%",
    "product_appearance": "乳白色液体"
  },
  {
    "internal_code": "CF450",
    "product_code": "2942000000",
    "customs_name": "固色剂",
    "components": "聚乙烯醇 80%\n水 20%",
    "product_appearance": "无色透明粘液"
  },
  {
    "internal_code": "CF188",
    "product_code": "3402420000",
    "customs_name": "非离子有机表面活性剂",
    "components": "乙二醇二醋酸酯111-55-7 50%\n非离子表面活性剂68603-25-8 50%",
    "product_appearance": "无色透明液"
  },
  {
    "internal_code": "T3071",
    "product_code": "3403910000",
    "customs_name": "防水剂",
    "components": "防水剂  CAS：65605-70-1  60%\n水  40%",
    "product_appearance": "乳白淡黄色液状"
  },
  {
    "internal_code": "CF792",
    "product_code": "",
    "customs_name": "阻燃剂",
    "components": "阻燃剂   14657-64-8  85%\n水  15%",
    "product_appearance": "透明粘稠液体"
  },
  {
    "internal_code": "LB-162-2",
    "product_code": "3403910000",
    "customs_name": "纺织柔软剂",
    "components": "聚二甲基硅氧烷（硅油）50%  9016-00-6，非离子乳化剂 10% 68213-23-0，水 40% 7732-18-5",
    "product_appearance": "浅黄色透明液体"
  },
  {
    "internal_code": "A-60JH",
    "product_code": "",
    "customs_name": "除油剂",
    "components": "脂肪醇聚氧烷基醚68439-46-3  80%\n水：20%",
    "product_appearance": "无色至浅黄色液体（朦）"
  },
  {
    "internal_code": "CF641",
    "product_code": "3402420000",
    "customs_name": "渗透剂",
    "components": "非离子表面活性剂68603-25-8   35%\n脂肪醇聚氧烷基醚68439-46-3  36%\n水 29%",
    "product_appearance": "无色透明粘液"
  },
  {
    "internal_code": "T73-GA",
    "product_code": "3402410000",
    "customs_name": "固色剂",
    "components": "聚羟丙基二甲基氯化铵，40%，CAS：25988-97-0\n水，60%，CAS：7732-18-0",
    "product_appearance": "黄色透明粘液"
  },
  {
    "internal_code": "F-54",
    "product_code": "3402420000",
    "customs_name": "非离子有机表面活性剂",
    "components": "非离子表面活性剂68603-25-8 8%\n脂肪醇聚氧烷基醚68439-46-3  10%\n水 72%",
    "product_appearance": "乳白色带蓝光乳液"
  },
  {
    "internal_code": "CF110B",
    "product_code": "3402420000",
    "customs_name": "非离子有机表面活性剂",
    "components": "聚乙二醇单油酸酯9004-96-0  20%\n非离子表面活性剂68603-25-8 80%",
    "product_appearance": "黄色透明液"
  },
  {
    "internal_code": "CF159D",
    "product_code": "3402420000",
    "customs_name": "非离子有机表面活性剂",
    "components": "聚乙二醇单油酸酯9004-96-0 40%\n脂肪醇聚氧烷基醚68439-46-3  60%",
    "product_appearance": "黄色半透明粘液"
  },
  {
    "internal_code": "T28-EA",
    "product_code": "3402420000",
    "customs_name": "非离子有机表面活性剂",
    "components": "聚乙二醇单油酸酯9004-96-0  90%\n非离子表面活性剂68603-25-8 10%",
    "product_appearance": "黄色透明液体"
  },
  {
    "internal_code": "CF1134",
    "product_code": "3403910000",
    "customs_name": "纺织助剂整理剂",
    "components": "聚氨盐与聚酯醚高分子复配物9016-88-0 20% \n水80%",
    "product_appearance": "乳白不透明液体"
  },
  {
    "internal_code": "CF067",
    "product_code": "2942000000",
    "customs_name": "螯合分散剂",
    "components": "葡萄糖酸钠527-07-1 30%\n葡萄糖 50-99-7  40%\n元明粉7757-82-6  30%",
    "product_appearance": "白色粉末"
  },
  {
    "internal_code": "H15-120",
    "product_code": "3402420000",
    "customs_name": "修补剂",
    "components": "乙二醇二醋酸酯111-55-7  25%\n非离子表面活性剂68603-25-8  75%",
    "product_appearance": "深黄色液体"
  },
  {
    "internal_code": "K68-AE",
    "product_code": "3402900000",
    "customs_name": "吸湿排汗整理剂",
    "components": "对苯二甲酸与乙二醇和聚乙二醇的聚合物 9016-88-0  15％ 水 85%",
    "product_appearance": "米白色不透明粘液"
  },
  {
    "internal_code": "F-182-9",
    "product_code": "3403910000",
    "customs_name": "纺织助剂整理剂",
    "components": "聚硅氧烷：22.5％ \n异构十三醇聚氧乙烯醚：4％\n水：73.5％",
    "product_appearance": "白色不透明液体"
  },
  {
    "internal_code": "F-118H",
    "product_code": "3402900000",
    "customs_name": "吸湿排汗整理剂",
    "components": "对苯二甲酸与乙二醇和聚乙二醇的聚合物 20% 9016-88-0 水 20%",
    "product_appearance": "黄色液体"
  },
  {
    "internal_code": "A-109H",
    "product_code": "3402420000",
    "customs_name": "非离子有机表面活性剂",
    "components": "非离子表面活性剂68603-25-8  60%\n脂肪醇聚氧烷基醚68439-46-3  20%\n水  20%",
    "product_appearance": "无色液体"
  },
  {
    "internal_code": "F-8R-2",
    "product_code": "3402900000",
    "customs_name": "吸湿排汗整理剂",
    "components": "柔软吸湿排汗整理剂：30％9016-88-0+水：70％  7732-18-5",
    "product_appearance": "白色不透明粘液"
  },
  {
    "internal_code": "CF804H",
    "product_code": "3403910000",
    "customs_name": "纺织助剂整理剂",
    "components": "丙烯酸酯共聚物 40%\n水 50%",
    "product_appearance": "白色带蓝光乳液"
  },
  {
    "internal_code": "CF804R",
    "product_code": "3403910000",
    "customs_name": "纺织助剂整理剂",
    "components": "丙烯酸酯共聚物 40%\n水 50%",
    "product_appearance": "白色带蓝光乳液"
  },
  {
    "internal_code": "A-109CA",
    "product_code": "3402420000",
    "customs_name": "除油剂",
    "components": "非离子表面活性剂68603-25-8 27%\n脂肪醇聚氧烷基醚68439-46-3  23%\n水  50%",
    "product_appearance": "浅黄色透明液"
  },
  {
    "internal_code": "HM148B",
    "product_code": "3403910000",
    "customs_name": "纺织助剂整理剂",
    "components": "聚丙烯酸酯95% 25608-33-7  水 5%",
    "product_appearance": "乳白不透明液体"
  },
  {
    "internal_code": "CF071H",
    "product_code": "3403910000",
    "customs_name": "纺织助剂消泡剂",
    "components": "聚醚环氧硅油9004-73-3 30%\n水  70%",
    "product_appearance": "粘稠不透明液体"
  },
  {
    "internal_code": "LP-2006",
    "product_code": "3403910000",
    "customs_name": "纺织柔软剂",
    "components": "聚硅氧烷：95％ 水：10％",
    "product_appearance": "微黄色粘稠液体"
  },
  {
    "internal_code": "HM116",
    "product_code": "3403910000",
    "customs_name": "纺织柔软剂",
    "components": "聚硅氧烷：100％",
    "product_appearance": "微黄色粘稠液体"
  },
  {
    "internal_code": "T73-GA",
    "product_code": "3402410000",
    "customs_name": "固色剂",
    "components": "二甲基二烯丙基氯化铵：26062-79-3，40%\n水：7732-18-0，60%",
    "product_appearance": "黄色透明粘液"
  },
  {
    "internal_code": "T153",
    "product_code": "3402900000",
    "customs_name": "固色剂",
    "components": "十二烷基苯磺酸钠：25155-30-0，40%\n分散剂：26545-58-4，5%\n水：7732-18-5，55%",
    "product_appearance": "黄色透明粘液"
  },
  {
    "internal_code": "GS56-01",
    "product_code": "3402900000",
    "customs_name": "固色剂",
    "components": "十二烷基苯磺酸钠：25155-30-0，37%\n分散剂：26545-58-4，8%\n水：7732-18-5，55%",
    "product_appearance": "棕黑色透明液"
  },
  {
    "internal_code": "LB-001D",
    "product_code": "3403910000",
    "customs_name": "纺织柔软剂",
    "components": "聚硅氧烷63148-62-9：8％+异构十三醇聚氧乙烯醚：3％9043-30-5 水 89%",
    "product_appearance": "淡黄色透明"
  },
  {
    "internal_code": "F-50C",
    "product_code": "3403910000",
    "customs_name": "纺织柔软剂",
    "components": "聚硅氧烷：25％+异构十三醇聚氧乙烯醚：5％9043-30-5+丙三醇：10％+水：60％",
    "product_appearance": "微黄色液体"
  },
  {
    "internal_code": "PW-242B",
    "product_code": "3403910000",
    "customs_name": "纺织柔软剂",
    "components": "聚硅氧烷：30％+异构十三醇聚氧乙烯醚：2％+水：68％9043-30-5",
    "product_appearance": "微黄色液体"
  },
  {
    "internal_code": "CF097",
    "product_code": "3402420000",
    "customs_name": "非离子有机表面活性剂",
    "components": "非离子表面活性剂68603-25-8  85%\n水  15%",
    "product_appearance": "无色液体"
  },
  {
    "internal_code": "GY-895",
    "product_code": "391000000",
    "customs_name": "有机硅柔软剂",
    "components": "异构十三醇聚氧乙烯醚:6％+聚硅氧烷:  24％+丙三醇：25％+水： 45％",
    "product_appearance": "无色至浅黄色透明液体"
  },
  {
    "internal_code": "GY-897",
    "product_code": "391000000",
    "customs_name": "有机硅柔软剂",
    "components": "异构十三醇聚氧乙烯醚：6％+聚硅氧烷：26％+丙三醇：20％+水：48％",
    "product_appearance": "无色至浅黄色透明液体"
  },
  {
    "internal_code": "B-74J",
    "product_code": "3403910000",
    "customs_name": "防水剂",
    "components": "丙烯酸氟烷基醋共聚物 65605-70-1 13% 水 87%",
    "product_appearance": "乳白色液体"
  },
  {
    "internal_code": "F-92D-6",
    "product_code": "3403910000",
    "customs_name": "纺织柔软剂",
    "components": "亲水软油68153-35-5：95％+水：5％",
    "product_appearance": "白色至微黄色不透明粘液"
  },
  {
    "internal_code": "CF1137",
    "product_code": "2942000000",
    "customs_name": "皂洗剂",
    "components": "乙烯基杂环改性聚合物 29297-55-0 30%  水 70%",
    "product_appearance": "黄色液体"
  },
  {
    "internal_code": "K187-KC",
    "product_code": "3402420000",
    "customs_name": "非离子有机表面活性剂",
    "components": "油酸112-80-1 15%\n非离子表面活性剂68603-25-8 10%\n水 75%",
    "product_appearance": "白色粉末"
  },
  {
    "internal_code": "XY-914",
    "product_code": "3403910000",
    "customs_name": "纺织助剂防染剂",
    "components": "聚乙二醇 25322-68-3  55% \n元明粉7757-82-6       10%\n水                   35%",
    "product_appearance": "黄色液体"
  },
  {
    "internal_code": "TF-8916LV",
    "product_code": "391000000",
    "customs_name": "有机硅柔软剂",
    "components": "聚硅氧烷 63148-62-9：30％+异构十三醇聚氧乙烯醚9043-30-5：8％+水：62％",
    "product_appearance": "无色至浅黄色透明液"
  },
  {
    "internal_code": "CF865/CF868",
    "product_code": "3402420000",
    "customs_name": "非离子有机表面活性剂",
    "components": "脂肪醇聚氧烷基醚68439-46-3  95%\n水   5%",
    "product_appearance": "黄色透明液体"
  },
  {
    "internal_code": "CF390",
    "product_code": "340391000",
    "customs_name": "纺织助剂整理剂",
    "components": "工业盐7647-14-5  50%\n元明粉7757-82-6  50%",
    "product_appearance": "白色颗粒"
  },
  {
    "internal_code": "CF1184",
    "product_code": "340391000",
    "customs_name": "纺织助剂整理剂",
    "components": "聚丙烯酸脂CAS号：9003-01-4 50%   水50%",
    "product_appearance": "乳白色液体"
  },
  {
    "internal_code": "CF278",
    "product_code": "3402420000",
    "customs_name": "非离子有机表面活性剂",
    "components": "非离子表面活性剂68603-25-8  95%\n水  5%",
    "product_appearance": "无色透明液体"
  },
  {
    "internal_code": "CF085",
    "product_code": "340391000",
    "customs_name": "纺织助剂整理剂",
    "components": "元明粉7757-82-6  50%\n柠檬酸77-92-9  50%",
    "product_appearance": "白色颗粒"
  },
  {
    "internal_code": "GY690",
    "product_code": "391000000",
    "customs_name": "有机硅柔软剂",
    "components": "聚硅氧烷63148-62-9：35％+异构十三醇聚氧乙烯醚9043-30-5：5％+水：60％",
    "product_appearance": "微黄色至黄色透明粘液"
  }
]